{
    "version": "https://jsonfeed.org/version/1",
    "title": "TheCrafters001",
    "description": "",
    "home_page_url": "https://thecrafters001.ga",
    "feed_url": "https://thecrafters001.ga/feed.json",
    "user_comment": "",
    "icon": "https://thecrafters001.ga/media/website/TC001.png",
    "author": {
        "name": "TheCrafters001"
    },
    "items": [
        {
            "id": "https://thecrafters001.ga/vw5pdhkuidotkq/",
            "url": "https://thecrafters001.ga/vw5pdhkuidotkq/",
            "title": "VW5pdHkuIDotKQ&#x3D;&#x3D;",
            "summary": "<h1 id=\"mcetoc_1e6mi229d5f\" align=\"center\">VW5pdHkuIDotKQ==</h1>\n",
            "content_html": "<h1 id=\"mcetoc_1e6mi229d5f\" align=\"center\">VW5pdHkuIDotKQ==</h1>\n\n<h1 id=\"mcetoc_1e6mi229d5g\" align=\"center\">VW5pdHkuIDotKQ==</h1>\n<h1 id=\"mcetoc_1e6mi229d5h\" align=\"center\">VW5pdHkuIDotKQ==</h1>\n<h1 id=\"mcetoc_1e6mi229d5i\" align=\"center\">VW5pdHkuIDotKQ==</h1>\n<h1 id=\"mcetoc_1e6mi229d5j\" align=\"center\">VW5pdHkuIDotKQ==</h1>\n<h1 id=\"mcetoc_1e6mi229d5k\" align=\"center\">VW5pdHkuIDotKQ==</h1>\n<h1 id=\"mcetoc_1e6mi229d5l\" align=\"center\">VW5pdHkuIDotKQ==</h1>\n<h1 id=\"mcetoc_1e6mi229d5m\" align=\"center\">VW5pdHkuIDotKQ==</h1>\n<h1 id=\"mcetoc_1e6mi229d5n\" align=\"center\">VW5pdHkuIDotKQ==</h1>\n<h1 id=\"mcetoc_1e6mi229d5o\" align=\"center\">VW5pdHkuIDotKQ==</h1>\n<h1 id=\"mcetoc_1e6mi229d5p\" align=\"center\">VW5pdHkuIDotKQ==</h1>\n<h1 id=\"mcetoc_1e6mi229d5q\" align=\"center\">VW5pdHkuIDotKQ==</h1>\n<h1 id=\"mcetoc_1e6mi229d5r\" align=\"center\">VW5pdHkuIDotKQ==</h1>\n<h1 id=\"mcetoc_1e6mi229d5s\" align=\"center\">VW5pdHkuIDotKQ==</h1>\n<h1 id=\"mcetoc_1e6mi229d5t\" align=\"center\">VW5pdHkuIDotKQ==</h1>\n<h1 id=\"mcetoc_1e6mi229d5u\" align=\"center\">VW5pdHkuIDotKQ==</h1>\n<h1 id=\"mcetoc_1e6mi229d5v\" align=\"center\">VW5pdHkuIDotKQ==</h1>\n<h1 id=\"mcetoc_1e6mi229d60\" align=\"center\">VW5pdHkuIDotKQ==</h1>\n<h1 id=\"mcetoc_1e6mi229d61\" align=\"center\">VW5pdHkuIDotKQ==</h1>\n<h1 id=\"mcetoc_1e6mi229d62\" align=\"center\">VW5pdHkuIDotKQ==</h1>\n<h1 id=\"mcetoc_1e6mi229d63\" align=\"center\">VW5pdHkuIDotKQ==</h1>\n<h1 id=\"mcetoc_1e6mi229d64\" align=\"center\">VW5pdHkuIDotKQ==</h1>\n<h1 id=\"mcetoc_1e6mi229d65\" align=\"center\">VW5pdHkuIDotKQ==</h1>\n<h1 id=\"mcetoc_1e6mi229d66\" align=\"center\">VW5pdHkuIDotKQ==</h1>\n<h1 id=\"mcetoc_1e6mi229d67\" align=\"center\">VW5pdHkuIDotKQ==</h1>\n<h1 id=\"mcetoc_1e6mi229d68\" align=\"center\">VW5pdHkuIDotKQ==</h1>\n<h1 id=\"mcetoc_1e6mi229d69\" align=\"center\">VW5pdHkuIDotKQ==</h1>\n<h1 id=\"mcetoc_1e6mi229d6a\" align=\"center\">VW5pdHkuIDotKQ==</h1>\n<h1 id=\"mcetoc_1e6mi229d6b\" align=\"center\">VW5pdHkuIDotKQ==</h1>\n<h1 id=\"mcetoc_1e6mi229d6c\" align=\"center\">VW5pdHkuIDotKQ==</h1>\n<h1 id=\"mcetoc_1e6mi229d6d\" align=\"center\">VW5pdHkuIDotKQ==</h1>\n<h1 id=\"mcetoc_1e6mi229d6e\" align=\"center\">VW5pdHkuIDotKQ==</h1>\n<h1 id=\"mcetoc_1e6mi229d6f\" align=\"center\">VW5pdHkuIDotKQ==</h1>\n<h1 id=\"mcetoc_1e6mi229d6g\" align=\"center\">VW5pdHkuIDotKQ==</h1>\n<h1 id=\"mcetoc_1e6mi229d6h\" align=\"center\">VW5pdHkuIDotKQ==</h1>\n<h1 id=\"mcetoc_1e6mi229d6i\" align=\"center\">VW5pdHkuIDotKQ==</h1>\n<h1 id=\"mcetoc_1e6mi229d6j\" align=\"center\">VW5pdHkuIDotKQ==</h1>\n<h1 id=\"mcetoc_1e6mi229d6k\" align=\"center\">VW5pdHkuIDotKQ==</h1>\n<h1 id=\"mcetoc_1e6mi229d6l\" align=\"center\">VW5pdHkuIDotKQ==</h1>\n<h1 id=\"mcetoc_1e6mi229d6m\" align=\"center\">VW5pdHkuIDotKQ==</h1>\n<h1 id=\"mcetoc_1e6mi229d6n\" align=\"center\">VW5pdHkuIDotKQ==</h1>\n<h1 id=\"mcetoc_1e6mi229d6o\" align=\"center\">VW5pdHkuIDotKQ==</h1>\n<h1 id=\"mcetoc_1e6mi229d6p\" align=\"center\">VW5pdHkuIDotKQ==</h1>\n<h1 id=\"mcetoc_1e6mi229d6q\" align=\"center\">VW5pdHkuIDotKQ==</h1>\n<h1 id=\"mcetoc_1e6mi229d6r\" align=\"center\">VW5pdHkuIDotKQ==</h1>\n<h1 id=\"mcetoc_1e6mi229d6s\" align=\"center\">VW5pdHkuIDotKQ==</h1>\n<h1 id=\"mcetoc_1e6mi229d6t\" align=\"center\">VW5pdHkuIDotKQ==</h1>\n<h1 id=\"mcetoc_1e6mi229d6u\" align=\"center\">VW5pdHkuIDotKQ==</h1>\n<h1 id=\"mcetoc_1e6mi229d6v\" align=\"center\">VW5pdHkuIDotKQ==</h1>\n<h1 id=\"mcetoc_1e6mi229d70\" align=\"center\">VW5pdHkuIDotKQ==</h1>\n<h1 id=\"mcetoc_1e6mi229d71\" align=\"center\">VW5pdHkuIDotKQ==</h1>\n<h1 id=\"mcetoc_1e6mi229d72\" align=\"center\">VW5pdHkuIDotKQ==</h1>\n<h1 id=\"mcetoc_1e6mi229d73\" align=\"center\">VW5pdHkuIDotKQ==</h1>\n<h1 id=\"mcetoc_1e6mi229d74\" align=\"center\">VW5pdHkuIDotKQ==</h1>\n<h1 id=\"mcetoc_1e6mi229d75\" align=\"center\">VW5pdHkuIDotKQ==</h1>\n<h1 id=\"mcetoc_1e6mi229d76\" align=\"center\">VW5pdHkuIDotKQ==</h1>\n<h1 id=\"mcetoc_1e6mi229d77\" align=\"center\">VW5pdHkuIDotKQ==</h1>\n<h1 id=\"mcetoc_1e6mi229d78\" align=\"center\">VW5pdHkuIDotKQ==</h1>\n<h1 id=\"mcetoc_1e6mi229d79\" align=\"center\">VW5pdHkuIDotKQ==</h1>\n<h1 id=\"mcetoc_1e6mi229d7a\" align=\"center\">VW5pdHkuIDotKQ==</h1>\n<h1 id=\"mcetoc_1e6mi229d7b\" align=\"center\">VW5pdHkuIDotKQ==</h1>\n<h1 id=\"mcetoc_1e6mi229d7c\" align=\"center\">VW5pdHkuIDotKQ==</h1>\n<h1 id=\"mcetoc_1e6mi229d7d\" align=\"center\">VW5pdHkuIDotKQ==</h1>\n<h1 id=\"mcetoc_1e6mi229d7e\" align=\"center\">VW5pdHkuIDotKQ==</h1>\n<h1 id=\"mcetoc_1e6mi229d7f\" align=\"center\">VW5pdHkuIDotKQ==</h1>\n<h1 id=\"mcetoc_1e6mi229d7g\" align=\"center\">VW5pdHkuIDotKQ==</h1>\n<h1 id=\"mcetoc_1e6mi229d7h\" align=\"center\">VW5pdHkuIDotKQ==</h1>\n<h1 id=\"mcetoc_1e6mi229d7i\" align=\"center\">VW5pdHkuIDotKQ==</h1>\n<h1 id=\"mcetoc_1e6mi229d7j\" align=\"center\">VW5pdHkuIDotKQ==</h1>\n<h1 id=\"mcetoc_1e6mi229d7k\" align=\"center\">VW5pdHkuIDotKQ==</h1>\n<h1 id=\"mcetoc_1e6mi229d7l\" align=\"center\">VW5pdHkuIDotKQ==</h1>\n<h1 id=\"mcetoc_1e6mi229d7m\" align=\"center\">VW5pdHkuIDotKQ==</h1>\n<h1 id=\"mcetoc_1e6mi229d7n\" align=\"center\">VW5pdHkuIDotKQ==</h1>\n<h1 id=\"mcetoc_1e6mi229d7o\" align=\"center\">VW5pdHkuIDotKQ==</h1>\n<h1 id=\"mcetoc_1e6mi229d7p\" align=\"center\">VW5pdHkuIDotKQ==</h1>\n<h1 id=\"mcetoc_1e6mi229d7q\" align=\"center\">VW5pdHkuIDotKQ==</h1>\n<h1 id=\"mcetoc_1e6mi229d7r\" align=\"center\">VW5pdHkuIDotKQ==</h1>\n<h1 id=\"mcetoc_1e6mi229d7s\" align=\"center\">VW5pdHkuIDotKQ==</h1>\n<h1 id=\"mcetoc_1e6mi229d7t\" align=\"center\">VW5pdHkuIDotKQ==</h1>\n<h1 id=\"mcetoc_1e6mi229d7u\" align=\"center\">VW5pdHkuIDotKQ==</h1>\n<h1 id=\"mcetoc_1e6mi229d7v\" align=\"center\">VW5pdHkuIDotKQ==</h1>\n<h1 id=\"mcetoc_1e6mi229d80\" align=\"center\">VW5pdHkuIDotKQ==</h1>\n<h1 id=\"mcetoc_1e6mi229d81\" align=\"center\">VW5pdHkuIDotKQ==</h1>\n<h1 id=\"mcetoc_1e6mi229d82\" align=\"center\">VW5pdHkuIDotKQ==</h1>\n<h1 id=\"mcetoc_1e6mi229d83\" align=\"center\">VW5pdHkuIDotKQ==</h1>\n<h1 id=\"mcetoc_1e6mi229d84\" align=\"center\">VW5pdHkuIDotKQ==</h1>\n<h1 id=\"mcetoc_1e6mi229d85\" align=\"center\">VW5pdHkuIDotKQ==</h1>\n<h1 id=\"mcetoc_1e6mi229d86\" align=\"center\">VW5pdHkuIDotKQ==</h1>\n<h1 id=\"mcetoc_1e6mi229d87\" align=\"center\">VW5pdHkuIDotKQ==</h1>\n<h1 id=\"mcetoc_1e6mi229d88\" align=\"center\">VW5pdHkuIDotKQ==</h1>\n<h1 id=\"mcetoc_1e6mi229d89\" align=\"center\">VW5pdHkuIDotKQ==</h1>\n<h1 id=\"mcetoc_1e6mi229d8a\" align=\"center\">VW5pdHkuIDotKQ==</h1>\n<h1 id=\"mcetoc_1e6mi229d8b\" align=\"center\">VW5pdHkuIDotKQ==</h1>\n<h1 id=\"mcetoc_1e6mi229d8c\" align=\"center\">VW5pdHkuIDotKQ==</h1>\n<h1 id=\"mcetoc_1e6mi229d8d\" align=\"center\">VW5pdHkuIDotKQ==</h1>\n<h1 id=\"mcetoc_1e6mi229d8e\" align=\"center\">VW5pdHkuIDotKQ==</h1>\n<h1 id=\"mcetoc_1e6mi229d8f\" align=\"center\">VW5pdHkuIDotKQ==</h1>\n<h1 id=\"mcetoc_1e6mi229d8g\" align=\"center\">VW5pdHkuIDotKQ==</h1>\n<h1 id=\"mcetoc_1e6mi229d8h\" align=\"center\">VW5pdHkuIDotKQ==</h1>\n<h1 id=\"mcetoc_1e6mi229d8i\" align=\"center\">VW5pdHkuIDotKQ==</h1>\n<h1 id=\"mcetoc_1e6mi229d8j\" align=\"center\">VW5pdHkuIDotKQ==</h1>\n<h1 id=\"mcetoc_1e6mi229d8k\" align=\"center\">VW5pdHkuIDotKQ==</h1>\n<h1 id=\"mcetoc_1e6mi229d8l\" align=\"center\">VW5pdHkuIDotKQ==</h1>\n<h1 id=\"mcetoc_1e6mi229d8m\" align=\"center\">VW5pdHkuIDotKQ==</h1>\n<h1 id=\"mcetoc_1e6mi229d8n\" align=\"center\">VW5pdHkuIDotKQ==</h1>\n<h1 id=\"mcetoc_1e6mi229d8o\" align=\"center\">VW5pdHkuIDotKQ==</h1>\n<h1 id=\"mcetoc_1e6mi229d8p\" align=\"center\">VW5pdHkuIDotKQ==</h1>\n<h1 id=\"mcetoc_1e6mi229d8q\" align=\"center\">VW5pdHkuIDotKQ==</h1>\n<h1 id=\"mcetoc_1e6mi229d8r\" align=\"center\">VW5pdHkuIDotKQ==</h1>\n<h1 id=\"mcetoc_1e6mi229d8s\" align=\"center\">VW5pdHkuIDotKQ==</h1>\n<h1 id=\"mcetoc_1e6mi229d8t\" align=\"center\">VW5pdHkuIDotKQ==</h1>\n<h1 id=\"mcetoc_1e6mi229d8u\" align=\"center\">VW5pdHkuIDotKQ==</h1>\n<h1 id=\"mcetoc_1e6mi229d8v\" align=\"center\">VW5pdHkuIDotKQ==</h1>\n<h1 id=\"mcetoc_1e6mi229d90\" align=\"center\">VW5pdHkuIDotKQ==</h1>\n<h1 id=\"mcetoc_1e6mi229d91\" align=\"center\">VW5pdHkuIDotKQ==</h1>\n<h1 id=\"mcetoc_1e6mi229d92\" align=\"center\">VW5pdHkuIDotKQ==</h1>\n<h1 id=\"mcetoc_1e6mi229d93\" align=\"center\">VW5pdHkuIDotKQ==</h1>\n<h1 id=\"mcetoc_1e6mi229d94\" align=\"center\">VW5pdHkuIDotKQ==</h1>\n<h1 id=\"mcetoc_1e6mi229d95\" align=\"center\">VW5pdHkuIDotKQ==</h1>\n<h1 id=\"mcetoc_1e6mi229d96\" align=\"center\">VW5pdHkuIDotKQ==</h1>\n<h1 id=\"mcetoc_1e6mi229d97\" align=\"center\">VW5pdHkuIDotKQ==</h1>\n<h1 id=\"mcetoc_1e6mi229d98\" align=\"center\">VW5pdHkuIDotKQ==</h1>\n<h1 id=\"mcetoc_1e6mi229d99\" align=\"center\">VW5pdHkuIDotKQ==</h1>\n<h1 id=\"mcetoc_1e6mi229d9a\" align=\"center\">VW5pdHkuIDotKQ==</h1>\n<h1 id=\"mcetoc_1e6mi229d9b\" align=\"center\">VW5pdHkuIDotKQ==</h1>\n<h1 id=\"mcetoc_1e6mi229d9c\" align=\"center\">VW5pdHkuIDotKQ==</h1>\n<h1 id=\"mcetoc_1e6mi229d9d\" align=\"center\">VW5pdHkuIDotKQ==</h1>\n<h1 id=\"mcetoc_1e6mi229d9e\" align=\"center\">VW5pdHkuIDotKQ==</h1>\n<h1 id=\"mcetoc_1e6mi229d9f\" align=\"center\">VW5pdHkuIDotKQ==</h1>\n<h1 id=\"mcetoc_1e6mi229d9g\" align=\"center\">VW5pdHkuIDotKQ==</h1>\n<h1 id=\"mcetoc_1e6mi229d9h\" align=\"center\">VW5pdHkuIDotKQ==</h1>\n<h1 id=\"mcetoc_1e6mi229d9i\" align=\"center\">VW5pdHkuIDotKQ==</h1>\n<h1 id=\"mcetoc_1e6mi229d9j\" align=\"center\">VW5pdHkuIDotKQ==</h1>\n<h1 id=\"mcetoc_1e6mi229d9k\" align=\"center\">VW5pdHkuIDotKQ==</h1>\n<h1 id=\"mcetoc_1e6mi229d9l\" align=\"center\">VW5pdHkuIDotKQ==</h1>\n<h1 id=\"mcetoc_1e6mi229d9m\" align=\"center\">VW5pdHkuIDotKQ==</h1>\n<h1 id=\"mcetoc_1e6mi229d9n\" align=\"center\">VW5pdHkuIDotKQ==</h1>\n<h1 id=\"mcetoc_1e6mi229d9o\" align=\"center\">VW5pdHkuIDotKQ==</h1>\n<h1 id=\"mcetoc_1e6mi229d9p\" align=\"center\">VW5pdHkuIDotKQ==</h1>\n<h1 id=\"mcetoc_1e6mi229d9q\" align=\"center\">VW5pdHkuIDotKQ==</h1>\n<h1 id=\"mcetoc_1e6mi229d9r\" align=\"center\">VW5pdHkuIDotKQ==</h1>\n<h1 id=\"mcetoc_1e6mi229d9s\" align=\"center\">VW5pdHkuIDotKQ==</h1>\n<h1 id=\"mcetoc_1e6mi229d9t\" align=\"center\">VW5pdHkuIDotKQ==</h1>\n<h1 id=\"mcetoc_1e6mi229e9u\" align=\"center\">VW5pdHkuIDotKQ==</h1>\n<h1 id=\"mcetoc_1e6mi229e9v\" align=\"center\">VW5pdHkuIDotKQ==</h1>\n<h1 id=\"mcetoc_1e6mi229ea0\" align=\"center\">VW5pdHkuIDotKQ==</h1>\n<h1 id=\"mcetoc_1e6mi229ea1\" align=\"center\">VW5pdHkuIDotKQ==</h1>\n<h1 id=\"mcetoc_1e6mi229ea2\" align=\"center\">VW5pdHkuIDotKQ==</h1>\n<h1 id=\"mcetoc_1e6mi229ea3\" align=\"center\">VW5pdHkuIDotKQ==</h1>\n<h1 id=\"mcetoc_1e6mi229ea4\" align=\"center\">VW5pdHkuIDotKQ==</h1>\n<h1 id=\"mcetoc_1e6mi229ea5\" align=\"center\">VW5pdHkuIDotKQ==</h1>\n<h1 id=\"mcetoc_1e6mi229ea6\" align=\"center\">VW5pdHkuIDotKQ==</h1>\n<h1 id=\"mcetoc_1e6mi229ea7\" align=\"center\">VW5pdHkuIDotKQ==</h1>\n<h1 id=\"mcetoc_1e6mi229ea8\" align=\"center\">VW5pdHkuIDotKQ==</h1>\n<h1 id=\"mcetoc_1e6mi229ea9\" align=\"center\">VW5pdHkuIDotKQ==</h1>\n<h1 id=\"mcetoc_1e6mi229eaa\" align=\"center\">VW5pdHkuIDotKQ==</h1>\n<h1 id=\"mcetoc_1e6mi229eab\" align=\"center\">VW5pdHkuIDotKQ==</h1>\n<h1 id=\"mcetoc_1e6mi229eac\" align=\"center\">VW5pdHkuIDotKQ==</h1>\n<h1 id=\"mcetoc_1e6mi229ead\" align=\"center\">VW5pdHkuIDotKQ==</h1>\n<h1 id=\"mcetoc_1e6mi229eae\" align=\"center\">VW5pdHkuIDotKQ==</h1>\n<h1 id=\"mcetoc_1e6mi229eaf\" align=\"center\">VW5pdHkuIDotKQ==</h1>\n<h1 id=\"mcetoc_1e6mi229eag\" align=\"center\">VW5pdHkuIDotKQ==</h1>\n<h1 id=\"mcetoc_1e6mi229eah\" align=\"center\">VW5pdHkuIDotKQ==</h1>\n<h1 id=\"mcetoc_1e6mi229eai\" align=\"center\">VW5pdHkuIDotKQ==</h1>\n<h1 id=\"mcetoc_1e6mi229eaj\" align=\"center\">VW5pdHkuIDotKQ==</h1>\n<h1 id=\"mcetoc_1e6mi229eak\" align=\"center\">VW5pdHkuIDotKQ==</h1>\n<h1 id=\"mcetoc_1e6mi229eal\" align=\"center\">VW5pdHkuIDotKQ==</h1>\n<h1 id=\"mcetoc_1e6mi229eam\" align=\"center\">VW5pdHkuIDotKQ==</h1>\n<h1 id=\"mcetoc_1e6mi229ean\" align=\"center\">VW5pdHkuIDotKQ==</h1>\n<h1 id=\"mcetoc_1e6mi229eao\" align=\"center\">VW5pdHkuIDotKQ==</h1>\n<h1 id=\"mcetoc_1e6mi229eap\" align=\"center\">VW5pdHkuIDotKQ==</h1>\n<h1 id=\"mcetoc_1e6mi229eaq\" align=\"center\">VW5pdHkuIDotKQ==</h1>\n<h1 id=\"mcetoc_1e6mi229ear\" align=\"center\">VW5pdHkuIDotKQ==</h1>\n<h1 id=\"mcetoc_1e6mi229eas\" align=\"center\">VW5pdHkuIDotKQ==</h1>\n<h1 id=\"mcetoc_1e6mi229eat\" align=\"center\">VW5pdHkuIDotKQ==</h1>\n<h1 id=\"mcetoc_1e6mi229eau\" align=\"center\">VW5pdHkuIDotKQ==</h1>\n<h1 id=\"mcetoc_1e6mi229eav\" align=\"center\">VW5pdHkuIDotKQ==</h1>\n<h1 id=\"mcetoc_1e6mi229eb0\" align=\"center\">VW5pdHkuIDotKQ==</h1>\n<h1 id=\"mcetoc_1e6mi229eb1\" align=\"center\">VW5pdHkuIDotKQ==</h1>\n<h1 id=\"mcetoc_1e6mi229eb2\" align=\"center\">VW5pdHkuIDotKQ==</h1>\n<h1 id=\"mcetoc_1e6mi229eb3\" align=\"center\">VW5pdHkuIDotKQ==</h1>\n<h1 id=\"mcetoc_1e6mi229eb4\" align=\"center\">VW5pdHkuIDotKQ==</h1>\n<h1 id=\"mcetoc_1e6mi229eb5\" align=\"center\">VW5pdHkuIDotKQ==</h1>\n<h1 id=\"mcetoc_1e6mi229eb6\" align=\"center\">VW5pdHkuIDotKQ==</h1>\n<h1 id=\"mcetoc_1e6mi229eb7\" align=\"center\">VW5pdHkuIDotKQ==</h1>\n<h1 id=\"mcetoc_1e6mi229eb8\" align=\"center\">VW5pdHkuIDotKQ==</h1>\n<h1 id=\"mcetoc_1e6mi229eb9\" align=\"center\">VW5pdHkuIDotKQ==</h1>\n<h1 id=\"mcetoc_1e6mi229eba\" align=\"center\">VW5pdHkuIDotKQ==</h1>\n<h1 id=\"mcetoc_1e6mi229ebb\" align=\"center\">VW5pdHkuIDotKQ==</h1>\n<h1 id=\"mcetoc_1e6mi229ebc\" align=\"center\">VW5pdHkuIDotKQ==</h1>\n<h1 id=\"mcetoc_1e6mi229ebd\" align=\"center\">VW5pdHkuIDotKQ==</h1>\n<h1 id=\"mcetoc_1e6mi229ebe\" align=\"center\">VW5pdHkuIDotKQ==</h1>\n<h1 id=\"mcetoc_1e6mi229ebf\" align=\"center\">VW5pdHkuIDotKQ==</h1>\n<h1 id=\"mcetoc_1e6mi229ebg\" align=\"center\">VW5pdHkuIDotKQ==</h1>\n<h1 id=\"mcetoc_1e6mi229ebh\" align=\"center\">VW5pdHkuIDotKQ==</h1>\n<h1 id=\"mcetoc_1e6mi229ebi\" align=\"center\">VW5pdHkuIDotKQ==</h1>\n<h1 id=\"mcetoc_1e6mi229ebj\" align=\"center\">VW5pdHkuIDotKQ==</h1>\n<h1 id=\"mcetoc_1e6mi229ebk\" align=\"center\">VW5pdHkuIDotKQ==</h1>\n<h1 id=\"mcetoc_1e6mi229ebl\" align=\"center\">VW5pdHkuIDotKQ==</h1>\n<h1 id=\"mcetoc_1e6mi229ebm\" align=\"center\">VW5pdHkuIDotKQ==</h1>\n<h1 id=\"mcetoc_1e6mi229ebn\" align=\"center\">VW5pdHkuIDotKQ==</h1>\n<h1 id=\"mcetoc_1e6mi229ebo\" align=\"center\">VW5pdHkuIDotKQ==</h1>\n<h1 id=\"mcetoc_1e6mi229ebp\" align=\"center\">VW5pdHkuIDotKQ==</h1>\n<h1 id=\"mcetoc_1e6mi229ebq\" align=\"center\">VW5pdHkuIDotKQ==</h1>\n<h1 id=\"mcetoc_1e6mi229ebr\" align=\"center\">VW5pdHkuIDotKQ==</h1>\n<h1 id=\"mcetoc_1e6mi229ebs\" align=\"center\">VW5pdHkuIDotKQ==</h1>\n<h1 id=\"mcetoc_1e6mi229ebt\" align=\"center\">VW5pdHkuIDotKQ==</h1>\n<h1 id=\"mcetoc_1e6mi229ebu\" align=\"center\">VW5pdHkuIDotKQ==</h1>\n<h1 id=\"mcetoc_1e6mi229ebv\" align=\"center\">VW5pdHkuIDotKQ==</h1>\n<h1 id=\"mcetoc_1e6mi229ec0\" align=\"center\">VW5pdHkuIDotKQ==</h1>\n<h1 id=\"mcetoc_1e6mi229ec1\" align=\"center\">VW5pdHkuIDotKQ==</h1>\n<h1 id=\"mcetoc_1e6mi229ec2\" align=\"center\">VW5pdHkuIDotKQ==</h1>\n<h1 id=\"mcetoc_1e6mi229ec3\" align=\"center\">VW5pdHkuIDotKQ==</h1>\n<h1 id=\"mcetoc_1e6mi229ec4\" align=\"center\">VW5pdHkuIDotKQ==</h1>\n<h1 id=\"mcetoc_1e6mi229ec5\" align=\"center\">VW5pdHkuIDotKQ==</h1>\n<h1 id=\"mcetoc_1e6mi229ec6\" align=\"center\">VW5pdHkuIDotKQ==</h1>\n<h1 id=\"mcetoc_1e6mi229ec7\" align=\"center\">VW5pdHkuIDotKQ==</h1>\n<h1 id=\"mcetoc_1e6mi229ec8\" align=\"center\">VW5pdHkuIDotKQ==</h1>\n<h1 id=\"mcetoc_1e6mi229ec9\" align=\"center\">VW5pdHkuIDotKQ==</h1>\n<h1 id=\"mcetoc_1e6mi229eca\" align=\"center\">VW5pdHkuIDotKQ==</h1>\n<h1 id=\"mcetoc_1e6mi229ecb\" align=\"center\">VW5pdHkuIDotKQ==</h1>\n<h1 id=\"mcetoc_1e6mi229ecc\" align=\"center\">VW5pdHkuIDotKQ==</h1>\n<h1 id=\"mcetoc_1e6mi229ecd\" align=\"center\">VW5pdHkuIDotKQ==</h1>\n<h1 id=\"mcetoc_1e6mi229ece\" align=\"center\">VW5pdHkuIDotKQ==</h1>\n<h1 id=\"mcetoc_1e6mi229ecf\" align=\"center\">VW5pdHkuIDotKQ==</h1>\n<h1 id=\"mcetoc_1e6mi229ecg\" align=\"center\">VW5pdHkuIDotKQ==</h1>\n<h1 id=\"mcetoc_1e6mi229ech\" align=\"center\">VW5pdHkuIDotKQ==</h1>\n<h1 id=\"mcetoc_1e6mi229eci\" align=\"center\">VW5pdHkuIDotKQ==</h1>\n<h1 id=\"mcetoc_1e6mi229ecj\" align=\"center\">VW5pdHkuIDotKQ==</h1>\n<h1 id=\"mcetoc_1e6mi229eck\" align=\"center\">VW5pdHkuIDotKQ==</h1>\n<h1 id=\"mcetoc_1e6mi229ecl\" align=\"center\">VW5pdHkuIDotKQ==</h1>\n<h1 id=\"mcetoc_1e6mi229ecm\" align=\"center\">VW5pdHkuIDotKQ==</h1>\n<h1 id=\"mcetoc_1e6mi229ecn\" align=\"center\">VW5pdHkuIDotKQ==</h1>\n<h1 id=\"mcetoc_1e6mi229eco\" align=\"center\">VW5pdHkuIDotKQ==</h1>\n<h1 id=\"mcetoc_1e6mi229ecp\" align=\"center\">VW5pdHkuIDotKQ==</h1>\n<h1 id=\"mcetoc_1e6mi229ecq\" align=\"center\">VW5pdHkuIDotKQ==</h1>\n<h1 id=\"mcetoc_1e6mi229ecr\" align=\"center\">VW5pdHkuIDotKQ==</h1>\n<h1 id=\"mcetoc_1e6mi229ecs\" align=\"center\">VW5pdHkuIDotKQ==</h1>\n<h1 id=\"mcetoc_1e6mi229ect\" align=\"center\">VW5pdHkuIDotKQ==</h1>\n<h1 id=\"mcetoc_1e6mi229ecu\" align=\"center\">VW5pdHkuIDotKQ==</h1>\n<h1 id=\"mcetoc_1e6mi229ecv\" align=\"center\">VW5pdHkuIDotKQ==</h1>\n<h1 id=\"mcetoc_1e6mi229ed0\" align=\"center\">VW5pdHkuIDotKQ==</h1>\n<h1 id=\"mcetoc_1e6mi229ed1\" align=\"center\">VW5pdHkuIDotKQ==</h1>\n<h1 id=\"mcetoc_1e6mi229ed2\" align=\"center\">VW5pdHkuIDotKQ==</h1>\n<h1 id=\"mcetoc_1e6mi229ed3\" align=\"center\">VW5pdHkuIDotKQ==</h1>\n<h1 id=\"mcetoc_1e6mi229ed4\" align=\"center\">VW5pdHkuIDotKQ==</h1>\n<h1 id=\"mcetoc_1e6mi229ed5\" align=\"center\">VW5pdHkuIDotKQ==</h1>\n<h1 id=\"mcetoc_1e6mi229ed6\" align=\"center\">VW5pdHkuIDotKQ==</h1>\n<h1 id=\"mcetoc_1e6mi229ed7\" align=\"center\">VW5pdHkuIDotKQ==</h1>\n<h1 id=\"mcetoc_1e6mi229ed8\" align=\"center\">VW5pdHkuIDotKQ==</h1>\n<h1 id=\"mcetoc_1e6mi229ed9\" align=\"center\">VW5pdHkuIDotKQ==</h1>\n<h1 id=\"mcetoc_1e6mi229eda\" align=\"center\">VW5pdHkuIDotKQ==</h1>\n<h1 id=\"mcetoc_1e6mi229edb\" align=\"center\">VW5pdHkuIDotKQ==</h1>\n<h1 id=\"mcetoc_1e6mi229edc\" align=\"center\">VW5pdHkuIDotKQ==</h1>\n<h1 id=\"mcetoc_1e6mi229edd\" align=\"center\">VW5pdHkuIDotKQ==</h1>\n<h1 id=\"mcetoc_1e6mi229ede\" align=\"center\">VW5pdHkuIDotKQ==</h1>\n<h1 id=\"mcetoc_1e6mi229edf\" align=\"center\">VW5pdHkuIDotKQ==</h1>\n<h1 id=\"mcetoc_1e6mi229edg\" align=\"center\">VW5pdHkuIDotKQ==</h1>\n<h1 id=\"mcetoc_1e6mi229edh\" align=\"center\">VW5pdHkuIDotKQ==</h1>\n<h1 id=\"mcetoc_1e6mi229edi\" align=\"center\">VW5pdHkuIDotKQ==</h1>\n<h1 id=\"mcetoc_1e6mi229edj\" align=\"center\">VW5pdHkuIDotKQ==</h1>\n<h1 id=\"mcetoc_1e6mi229edk\" align=\"center\">VW5pdHkuIDotKQ==</h1>\n<h1 id=\"mcetoc_1e6mi229edl\" align=\"center\">VW5pdHkuIDotKQ==</h1>\n<h1 id=\"mcetoc_1e6mi229edm\" align=\"center\">VW5pdHkuIDotKQ==</h1>\n<h1 id=\"mcetoc_1e6mi229edn\" align=\"center\">VW5pdHkuIDotKQ==</h1>\n<h1 id=\"mcetoc_1e6mi229edo\" align=\"center\">VW5pdHkuIDotKQ==</h1>\n<h1 id=\"mcetoc_1e6mi229edp\" align=\"center\">VW5pdHkuIDotKQ==</h1>\n<h1 id=\"mcetoc_1e6mi229edq\" align=\"center\">VW5pdHkuIDotKQ==</h1>\n<h1 id=\"mcetoc_1e6mi229edr\" align=\"center\">VW5pdHkuIDotKQ==</h1>\n<h1 id=\"mcetoc_1e6mi229eds\" align=\"center\">VW5pdHkuIDotKQ==</h1>\n<h1 id=\"mcetoc_1e6mi229edt\" align=\"center\">VW5pdHkuIDotKQ==</h1>\n<h1 id=\"mcetoc_1e6mi229edu\" align=\"center\">VW5pdHkuIDotKQ==</h1>\n<h1 id=\"mcetoc_1e6mi229edv\" align=\"center\">VW5pdHkuIDotKQ==</h1>\n<h1 id=\"mcetoc_1e6mi229ee0\" align=\"center\">VW5pdHkuIDotKQ==</h1>\n<h1 id=\"mcetoc_1e6mi229ee1\" align=\"center\">VW5pdHkuIDotKQ==</h1>\n<h1 id=\"mcetoc_1e6mi229ee2\" align=\"center\">VW5pdHkuIDotKQ==</h1>\n<h1 id=\"mcetoc_1e6mi229ee3\" align=\"center\">VW5pdHkuIDotKQ==</h1>\n<h1 id=\"mcetoc_1e6mi229ee4\" align=\"center\">VW5pdHkuIDotKQ==</h1>\n<h1 id=\"mcetoc_1e6mi229ee5\" align=\"center\">VW5pdHkuIDotKQ==</h1>\n<h1 id=\"mcetoc_1e6mi229ee6\" align=\"center\">VW5pdHkuIDotKQ==</h1>\n<h1 id=\"mcetoc_1e6mi229ee7\" align=\"center\">VW5pdHkuIDotKQ==</h1>\n<h1 id=\"mcetoc_1e6mi229ee8\" align=\"center\">VW5pdHkuIDotKQ==</h1>\n<h1 id=\"mcetoc_1e6mi229ee9\" align=\"center\">VW5pdHkuIDotKQ==</h1>\n<h1 id=\"mcetoc_1e6mi229eea\" align=\"center\">VW5pdHkuIDotKQ==</h1>\n<h1 id=\"mcetoc_1e6mi229eeb\" align=\"center\">VW5pdHkuIDotKQ==</h1>\n<h1 id=\"mcetoc_1e6mi229eec\" align=\"center\">VW5pdHkuIDotKQ==</h1>\n<h1 id=\"mcetoc_1e6mi229eed\" align=\"center\">VW5pdHkuIDotKQ==</h1>\n<h1 id=\"mcetoc_1e6mi229eee\" align=\"center\">VW5pdHkuIDotKQ==</h1>\n<h1 id=\"mcetoc_1e6mi229eef\" align=\"center\">VW5pdHkuIDotKQ==</h1>\n<h1 id=\"mcetoc_1e6mi229eeg\" align=\"center\">VW5pdHkuIDotKQ==</h1>\n<h1 id=\"mcetoc_1e6mi229eeh\" align=\"center\">VW5pdHkuIDotKQ==</h1>\n<h1 id=\"mcetoc_1e6mi229eei\" align=\"center\">VW5pdHkuIDotKQ==</h1>\n<h1 id=\"mcetoc_1e6mi229eej\" align=\"center\">VW5pdHkuIDotKQ==</h1>\n<h1 id=\"mcetoc_1e6mi229eek\" align=\"center\">VW5pdHkuIDotKQ==</h1>\n<h1 id=\"mcetoc_1e6mi229eel\" align=\"center\">VW5pdHkuIDotKQ==</h1>\n<h1 id=\"mcetoc_1e6mi229eem\" align=\"center\">VW5pdHkuIDotKQ==</h1>\n<h1 id=\"mcetoc_1e6mi229een\" align=\"center\">VW5pdHkuIDotKQ==</h1>\n<h1 id=\"mcetoc_1e6mi229eeo\" align=\"center\">VW5pdHkuIDotKQ==</h1>\n<h1 id=\"mcetoc_1e6mi229eep\" align=\"center\">VW5pdHkuIDotKQ==</h1>\n<h1 id=\"mcetoc_1e6mi229eeq\" align=\"center\">VW5pdHkuIDotKQ==</h1>\n<h1 id=\"mcetoc_1e6mi229eer\" align=\"center\">VW5pdHkuIDotKQ==</h1>\n<h1 id=\"mcetoc_1e6mi229ees\" align=\"center\">VW5pdHkuIDotKQ==</h1>\n<h1 id=\"mcetoc_1e6mi229eet\" align=\"center\">VW5pdHkuIDotKQ==</h1>\n<h1 id=\"mcetoc_1e6mi229eeu\" align=\"center\">VW5pdHkuIDotKQ==</h1>\n<h1 id=\"mcetoc_1e6mi229eev\" align=\"center\">VW5pdHkuIDotKQ==</h1>\n<h1 id=\"mcetoc_1e6mi229ef0\" align=\"center\">VW5pdHkuIDotKQ==</h1>\n<h1 id=\"mcetoc_1e6mi229ef1\" align=\"center\">VW5pdHkuIDotKQ==</h1>\n<h1 id=\"mcetoc_1e6mi229ef2\" align=\"center\">VW5pdHkuIDotKQ==</h1>\n<h1 id=\"mcetoc_1e6mi229ef3\" align=\"center\">VW5pdHkuIDotKQ==</h1>\n<h1 id=\"mcetoc_1e6mi229ef4\" align=\"center\">VW5pdHkuIDotKQ==</h1>\n<h1 id=\"mcetoc_1e6mi229ef5\" align=\"center\">VW5pdHkuIDotKQ==</h1>\n<h1 id=\"mcetoc_1e6mi229ef6\" align=\"center\">VW5pdHkuIDotKQ==</h1>\n<h1 id=\"mcetoc_1e6mi229ef7\" align=\"center\">VW5pdHkuIDotKQ==</h1>\n<h1 id=\"mcetoc_1e6mi229ef8\" align=\"center\">VW5pdHkuIDotKQ==</h1>\n<h1 id=\"mcetoc_1e6mi229ef9\" align=\"center\">VW5pdHkuIDotKQ==</h1>\n<h1 id=\"mcetoc_1e6mi229efa\" align=\"center\">VW5pdHkuIDotKQ==</h1>\n<h1 id=\"mcetoc_1e6mi229efb\" align=\"center\">VW5pdHkuIDotKQ==</h1>\n<h1 id=\"mcetoc_1e6mi229efc\" align=\"center\">VW5pdHkuIDotKQ==</h1>\n<h1 id=\"mcetoc_1e6mi229efd\" align=\"center\">VW5pdHkuIDotKQ==</h1>\n<h1 id=\"mcetoc_1e6mi229efe\" align=\"center\">VW5pdHkuIDotKQ==</h1>\n<h1 id=\"mcetoc_1e6mi229eff\" align=\"center\">VW5pdHkuIDotKQ==</h1>\n<h1 id=\"mcetoc_1e6mi229efg\" align=\"center\">VW5pdHkuIDotKQ==</h1>\n<h1 id=\"mcetoc_1e6mi229efh\" align=\"center\">VW5pdHkuIDotKQ==</h1>\n<h1 id=\"mcetoc_1e6mi229efi\" align=\"center\">VW5pdHkuIDotKQ==</h1>\n<h1 id=\"mcetoc_1e6mi229efj\" align=\"center\">VW5pdHkuIDotKQ==</h1>\n<h1 id=\"mcetoc_1e6mi229efk\" align=\"center\">VW5pdHkuIDotKQ==</h1>\n<h1 id=\"mcetoc_1e6mi229efl\" align=\"center\">VW5pdHkuIDotKQ==</h1>\n<h1 id=\"mcetoc_1e6mi229efm\" align=\"center\">VW5pdHkuIDotKQ==</h1>\n<h1 id=\"mcetoc_1e6mi229efn\" align=\"center\">VW5pdHkuIDotKQ==</h1>\n<h1 id=\"mcetoc_1e6mi229efo\" align=\"center\">VW5pdHkuIDotKQ==</h1>\n<h1 id=\"mcetoc_1e6mi229efp\" align=\"center\">VW5pdHkuIDotKQ==</h1>\n<h1 id=\"mcetoc_1e6mi229efq\" align=\"center\">VW5pdHkuIDotKQ==</h1>\n<h1 id=\"mcetoc_1e6mi229efr\" align=\"center\">VW5pdHkuIDotKQ==</h1>\n<h1 id=\"mcetoc_1e6mi229efs\" align=\"center\">VW5pdHkuIDotKQ==</h1>\n<h1 id=\"mcetoc_1e6mi229eft\" align=\"center\">VW5pdHkuIDotKQ==</h1>\n<h1 id=\"mcetoc_1e6mi229efu\" align=\"center\">VW5pdHkuIDotKQ==</h1>\n<h1 id=\"mcetoc_1e6mi229efv\" align=\"center\">VW5pdHkuIDotKQ==</h1>\n<h1 id=\"mcetoc_1e6mi229eg0\" align=\"center\">VW5pdHkuIDotKQ==</h1>\n<h1 id=\"mcetoc_1e6mi229eg1\" align=\"center\">VW5pdHkuIDotKQ==</h1>\n<h1 id=\"mcetoc_1e6mi229eg2\" align=\"center\">VW5pdHkuIDotKQ==</h1>\n<h1 id=\"mcetoc_1e6mi229eg3\" align=\"center\">VW5pdHkuIDotKQ==</h1>\n<h1 id=\"mcetoc_1e6mi229eg4\" align=\"center\">VW5pdHkuIDotKQ==</h1>\n<h1 id=\"mcetoc_1e6mi229eg5\" align=\"center\">VW5pdHkuIDotKQ==</h1>\n<h1 id=\"mcetoc_1e6mi229eg6\" align=\"center\">VW5pdHkuIDotKQ==</h1>\n<h1 id=\"mcetoc_1e6mi229eg7\" align=\"center\">VW5pdHkuIDotKQ==</h1>\n<h1 id=\"mcetoc_1e6mi229eg8\" align=\"center\">VW5pdHkuIDotKQ==</h1>\n<h1 id=\"mcetoc_1e6mi229eg9\" align=\"center\">VW5pdHkuIDotKQ==</h1>\n<h1 id=\"mcetoc_1e6mi229ega\" align=\"center\">VW5pdHkuIDotKQ==</h1>\n<h1 id=\"mcetoc_1e6mi229egb\" align=\"center\">VW5pdHkuIDotKQ==</h1>\n<h1 id=\"mcetoc_1e6mi229egc\" align=\"center\">VW5pdHkuIDotKQ==</h1>\n<h1 id=\"mcetoc_1e6mi229egd\" align=\"center\">VW5pdHkuIDotKQ==</h1>\n<h1 id=\"mcetoc_1e6mi229ege\" align=\"center\">VW5pdHkuIDotKQ==</h1>\n<h1 id=\"mcetoc_1e6mi229egf\" align=\"center\">VW5pdHkuIDotKQ==</h1>\n<h1 id=\"mcetoc_1e6mi229egg\" align=\"center\">VW5pdHkuIDotKQ==</h1>\n<h1 id=\"mcetoc_1e6mi229egh\" align=\"center\">VW5pdHkuIDotKQ==</h1>\n<h1 id=\"mcetoc_1e6mi229egi\" align=\"center\">VW5pdHkuIDotKQ==</h1>\n<h1 id=\"mcetoc_1e6mi229egj\" align=\"center\">VW5pdHkuIDotKQ==</h1>\n<h1 id=\"mcetoc_1e6mi229egk\" align=\"center\">VW5pdHkuIDotKQ==</h1>\n<h1 id=\"mcetoc_1e6mi229egl\" align=\"center\">VW5pdHkuIDotKQ==</h1>\n<h1 id=\"mcetoc_1e6mi229egm\" align=\"center\">VW5pdHkuIDotKQ==</h1>\n<h1 id=\"mcetoc_1e6mi229egn\" align=\"center\">VW5pdHkuIDotKQ==</h1>\n<h1 id=\"mcetoc_1e6mi229ego\" align=\"center\">VW5pdHkuIDotKQ==</h1>\n<h1 id=\"mcetoc_1e6mi229egp\" align=\"center\">VW5pdHkuIDotKQ==</h1>\n<h1 id=\"mcetoc_1e6mi229egq\" align=\"center\">VW5pdHkuIDotKQ==</h1>\n<h1 id=\"mcetoc_1e6mi229egr\" align=\"center\">VW5pdHkuIDotKQ==</h1>\n<h1 id=\"mcetoc_1e6mi229egs\" align=\"center\">VW5pdHkuIDotKQ==</h1>\n<h1 id=\"mcetoc_1e6mi229egt\" align=\"center\">VW5pdHkuIDotKQ==</h1>\n<h1 id=\"mcetoc_1e6mi229egu\" align=\"center\">VW5pdHkuIDotKQ==</h1>\n<h1 id=\"mcetoc_1e6mi229egv\" align=\"center\">VW5pdHkuIDotKQ==</h1>\n<h1 id=\"mcetoc_1e6mi229eh0\" align=\"center\">VW5pdHkuIDotKQ==</h1>\n<h1 id=\"mcetoc_1e6mi229eh1\" align=\"center\">VW5pdHkuIDotKQ==</h1>\n<h1 id=\"mcetoc_1e6mi229eh2\" align=\"center\">VW5pdHkuIDotKQ==</h1>\n<h1 id=\"mcetoc_1e6mi229eh3\" align=\"center\">VW5pdHkuIDotKQ==</h1>\n<h1 id=\"mcetoc_1e6mi229eh4\" align=\"center\">VW5pdHkuIDotKQ==</h1>\n<h1 id=\"mcetoc_1e6mi229eh5\" align=\"center\">VW5pdHkuIDotKQ==</h1>\n<h1 id=\"mcetoc_1e6mi229eh6\" align=\"center\">VW5pdHkuIDotKQ==</h1>\n<h1 id=\"mcetoc_1e6mi229eh7\" align=\"center\">VW5pdHkuIDotKQ==</h1>\n<h1 id=\"mcetoc_1e6mi229eh8\" align=\"center\">VW5pdHkuIDotKQ==</h1>\n<h1 id=\"mcetoc_1e6mi229eh9\" align=\"center\">VW5pdHkuIDotKQ==</h1>\n<h1 id=\"mcetoc_1e6mi229eha\" align=\"center\">VW5pdHkuIDotKQ==</h1>\n<h1 id=\"mcetoc_1e6mi229ehb\" align=\"center\">VW5pdHkuIDotKQ==</h1>\n<h1 id=\"mcetoc_1e6mi229ehc\" align=\"center\">VW5pdHkuIDotKQ==</h1>\n<h1 id=\"mcetoc_1e6mi229ehd\" align=\"center\">VW5pdHkuIDotKQ==</h1>\n<h1 id=\"mcetoc_1e6mi229ehe\" align=\"center\">VW5pdHkuIDotKQ==</h1>\n<h1 id=\"mcetoc_1e6mi229ehf\" align=\"center\">VW5pdHkuIDotKQ==</h1>\n<h1 id=\"mcetoc_1e6mi229ehg\" align=\"center\">VW5pdHkuIDotKQ==</h1>\n<h1 id=\"mcetoc_1e6mi229ehh\" align=\"center\">VW5pdHkuIDotKQ==</h1>\n<h1 id=\"mcetoc_1e6mi229ehi\" align=\"center\">VW5pdHkuIDotKQ==</h1>\n<h1 id=\"mcetoc_1e6mi229ehj\" align=\"center\">VW5pdHkuIDotKQ==</h1>\n<h1 id=\"mcetoc_1e6mi229ehk\" align=\"center\">VW5pdHkuIDotKQ==</h1>\n<h1 id=\"mcetoc_1e6mi229ehl\" align=\"center\">VW5pdHkuIDotKQ==</h1>\n<h1 id=\"mcetoc_1e6mi229ehm\" align=\"center\">VW5pdHkuIDotKQ==</h1>\n<h1 id=\"mcetoc_1e6mi229ehn\" align=\"center\">VW5pdHkuIDotKQ==</h1>\n<h1 id=\"mcetoc_1e6mi229eho\" align=\"center\">VW5pdHkuIDotKQ==</h1>\n<h1 id=\"mcetoc_1e6mi229ehp\" align=\"center\">VW5pdHkuIDotKQ==</h1>\n<h1 id=\"mcetoc_1e6mi229ehq\" align=\"center\">VW5pdHkuIDotKQ==</h1>\n<h1 id=\"mcetoc_1e6mi229ehr\" align=\"center\">VW5pdHkuIDotKQ==</h1>\n<h1 id=\"mcetoc_1e6mi229ehs\" align=\"center\">VW5pdHkuIDotKQ==</h1>\n<h1 id=\"mcetoc_1e6mi229eht\" align=\"center\">VW5pdHkuIDotKQ==</h1>\n<h1 id=\"mcetoc_1e6mi229ehu\" align=\"center\">VW5pdHkuIDotKQ==</h1>\n<h1 id=\"mcetoc_1e6mi229ehv\" align=\"center\">VW5pdHkuIDotKQ==</h1>\n<h1 id=\"mcetoc_1e6mi229ei0\" align=\"center\">VW5pdHkuIDotKQ==</h1>\n<h1 id=\"mcetoc_1e6mi229ei1\" align=\"center\">VW5pdHkuIDotKQ==</h1>\n<h1 id=\"mcetoc_1e6mi229ei2\" align=\"center\">VW5pdHkuIDotKQ==</h1>\n<h1 id=\"mcetoc_1e6mi229ei3\" align=\"center\">VW5pdHkuIDotKQ==</h1>\n<h1 id=\"mcetoc_1e6mi229ei4\" align=\"center\">VW5pdHkuIDotKQ==</h1>\n<h1 id=\"mcetoc_1e6mi229fi5\" align=\"center\">VW5pdHkuIDotKQ==</h1>\n<h1 id=\"mcetoc_1e6mi229fi6\" align=\"center\">VW5pdHkuIDotKQ==</h1>\n<h1 id=\"mcetoc_1e6mi229fi7\" align=\"center\">VW5pdHkuIDotKQ==</h1>\n<h1 id=\"mcetoc_1e6mi229fi8\" align=\"center\">VW5pdHkuIDotKQ==</h1>\n<h1 id=\"mcetoc_1e6mi229fi9\" align=\"center\">VW5pdHkuIDotKQ==</h1>\n<h1 id=\"mcetoc_1e6mi229fia\" align=\"center\">VW5pdHkuIDotKQ==</h1>\n<h1 id=\"mcetoc_1e6mi229fib\" align=\"center\">VW5pdHkuIDotKQ==</h1>\n<h1 id=\"mcetoc_1e6mi229fic\" align=\"center\">VW5pdHkuIDotKQ==</h1>\n<h1 id=\"mcetoc_1e6mi229fid\" align=\"center\">VW5pdHkuIDotKQ==</h1>\n<h1 id=\"mcetoc_1e6mi229fie\" align=\"center\">VW5pdHkuIDotKQ==</h1>\n<h1 id=\"mcetoc_1e6mi229fif\" align=\"center\">VW5pdHkuIDotKQ==</h1>\n<h1 id=\"mcetoc_1e6mi229fig\" align=\"center\">VW5pdHkuIDotKQ==</h1>\n<h1 id=\"mcetoc_1e6mi229fih\" align=\"center\">VW5pdHkuIDotKQ==</h1>\n<h1 id=\"mcetoc_1e6mi229fii\" align=\"center\">VW5pdHkuIDotKQ==</h1>\n<h1 id=\"mcetoc_1e6mi229fij\" align=\"center\">VW5pdHkuIDotKQ==</h1>\n<h1 id=\"mcetoc_1e6mi229fik\" align=\"center\">VW5pdHkuIDotKQ==</h1>\n<h1 id=\"mcetoc_1e6mi229fil\" align=\"center\">VW5pdHkuIDotKQ==</h1>\n<h1 id=\"mcetoc_1e6mi229fim\" align=\"center\">VW5pdHkuIDotKQ==</h1>\n<h1 id=\"mcetoc_1e6mi229fin\" align=\"center\">VW5pdHkuIDotKQ==</h1>\n<h1 id=\"mcetoc_1e6mi229fio\" align=\"center\">VW5pdHkuIDotKQ==</h1>\n<h1 id=\"mcetoc_1e6mi229fip\" align=\"center\">VW5pdHkuIDotKQ==</h1>\n<h1 id=\"mcetoc_1e6mi229fiq\" align=\"center\">VW5pdHkuIDotKQ==</h1>\n<h1 id=\"mcetoc_1e6mi229fir\" align=\"center\">VW5pdHkuIDotKQ==</h1>\n<h1 id=\"mcetoc_1e6mi229fis\" align=\"center\">VW5pdHkuIDotKQ==</h1>\n<h1 id=\"mcetoc_1e6mi229fit\" align=\"center\">VW5pdHkuIDotKQ==</h1>\n<h1 id=\"mcetoc_1e6mi229fiu\" align=\"center\">VW5pdHkuIDotKQ==</h1>\n<h1 id=\"mcetoc_1e6mi229fiv\" align=\"center\">VW5pdHkuIDotKQ==</h1>\n<h1 id=\"mcetoc_1e6mi229fj0\" align=\"center\">VW5pdHkuIDotKQ==</h1>\n<h1 id=\"mcetoc_1e6mi229fj1\" align=\"center\">VW5pdHkuIDotKQ==</h1>\n<h1 id=\"mcetoc_1e6mi229fj2\" align=\"center\">VW5pdHkuIDotKQ==</h1>\n<h1 id=\"mcetoc_1e6mi229fj3\" align=\"center\">VW5pdHkuIDotKQ==</h1>\n<h1 id=\"mcetoc_1e6mi229fj4\" align=\"center\">VW5pdHkuIDotKQ==</h1>\n<h1 id=\"mcetoc_1e6mi229fj5\" align=\"center\">VW5pdHkuIDotKQ==</h1>\n<h1 id=\"mcetoc_1e6mi229fj6\" align=\"center\">VW5pdHkuIDotKQ==</h1>\n<h1 id=\"mcetoc_1e6mi229fj7\" align=\"center\">VW5pdHkuIDotKQ==</h1>\n<h1 id=\"mcetoc_1e6mi229fj8\" align=\"center\">VW5pdHkuIDotKQ==</h1>\n<h1 id=\"mcetoc_1e6mi229fj9\" align=\"center\">VW5pdHkuIDotKQ==</h1>\n<h1 id=\"mcetoc_1e6mi229fja\" align=\"center\">VW5pdHkuIDotKQ==</h1>\n<h1 id=\"mcetoc_1e6mi229fjb\" align=\"center\">VW5pdHkuIDotKQ==</h1>\n<h1 id=\"mcetoc_1e6mi229fjc\" align=\"center\">VW5pdHkuIDotKQ==</h1>\n<h1 id=\"mcetoc_1e6mi229fjd\" align=\"center\">VW5pdHkuIDotKQ==</h1>\n<h1 id=\"mcetoc_1e6mi229fje\" align=\"center\">VW5pdHkuIDotKQ==</h1>\n<h1 id=\"mcetoc_1e6mi229fjf\" align=\"center\">VW5pdHkuIDotKQ==</h1>\n<h1 id=\"mcetoc_1e6mi229fjg\" align=\"center\">VW5pdHkuIDotKQ==</h1>\n<h1 id=\"mcetoc_1e6mi229fjh\" align=\"center\">VW5pdHkuIDotKQ==</h1>\n<h1 id=\"mcetoc_1e6mi229fji\" align=\"center\">VW5pdHkuIDotKQ==</h1>\n<h1 id=\"mcetoc_1e6mi229fjj\" align=\"center\">VW5pdHkuIDotKQ==</h1>\n<h1 id=\"mcetoc_1e6mi229fjk\" align=\"center\">VW5pdHkuIDotKQ==</h1>\n<h1 id=\"mcetoc_1e6mi229fjl\" align=\"center\">VW5pdHkuIDotKQ==</h1>\n<h1 id=\"mcetoc_1e6mi229fjm\" align=\"center\">VW5pdHkuIDotKQ==</h1>\n<h1 id=\"mcetoc_1e6mi229fjn\" align=\"center\">VW5pdHkuIDotKQ==</h1>\n<h1 id=\"mcetoc_1e6mi229fjo\" align=\"center\">VW5pdHkuIDotKQ==</h1>\n<h1 id=\"mcetoc_1e6mi229fjp\" align=\"center\">VW5pdHkuIDotKQ==</h1>\n<h1 id=\"mcetoc_1e6mi229fjq\" align=\"center\">VW5pdHkuIDotKQ==</h1>\n<h1 id=\"mcetoc_1e6mi229fjr\" align=\"center\">VW5pdHkuIDotKQ==</h1>\n<h1 id=\"mcetoc_1e6mi229fjs\" align=\"center\">VW5pdHkuIDotKQ==</h1>\n<h1 id=\"mcetoc_1e6mi229fjt\" align=\"center\">VW5pdHkuIDotKQ==</h1>\n<h1 id=\"mcetoc_1e6mi229fju\" align=\"center\">VW5pdHkuIDotKQ==</h1>\n<h1 id=\"mcetoc_1e6mi229fjv\" align=\"center\">VW5pdHkuIDotKQ==</h1>\n<h1 id=\"mcetoc_1e6mi229fk0\" align=\"center\">VW5pdHkuIDotKQ==</h1>\n<h1 id=\"mcetoc_1e6mi229fk1\" align=\"center\">VW5pdHkuIDotKQ==</h1>\n<h1 id=\"mcetoc_1e6mi229fk2\" align=\"center\">VW5pdHkuIDotKQ==</h1>\n<h1 id=\"mcetoc_1e6mi229fk3\" align=\"center\">VW5pdHkuIDotKQ==</h1>\n<h1 id=\"mcetoc_1e6mi229fk4\" align=\"center\">VW5pdHkuIDotKQ==</h1>\n<h1 id=\"mcetoc_1e6mi229fk5\" align=\"center\">VW5pdHkuIDotKQ==</h1>\n<h1 id=\"mcetoc_1e6mi229fk6\" align=\"center\">VW5pdHkuIDotKQ==</h1>\n<h1 id=\"mcetoc_1e6mi229fk7\" align=\"center\">VW5pdHkuIDotKQ==</h1>\n<h1 id=\"mcetoc_1e6mi229fk8\" align=\"center\">VW5pdHkuIDotKQ==</h1>\n<h1 id=\"mcetoc_1e6mi229fk9\" align=\"center\">VW5pdHkuIDotKQ==</h1>\n<h1 id=\"mcetoc_1e6mi229fka\" align=\"center\">VW5pdHkuIDotKQ==</h1>\n<h1 id=\"mcetoc_1e6mi229fkb\" align=\"center\">VW5pdHkuIDotKQ==</h1>\n<h1 id=\"mcetoc_1e6mi229fkc\" align=\"center\">VW5pdHkuIDotKQ==</h1>\n<h1 id=\"mcetoc_1e6mi229fkd\" align=\"center\">VW5pdHkuIDotKQ==</h1>\n<h1 id=\"mcetoc_1e6mi229fke\" align=\"center\">VW5pdHkuIDotKQ==</h1>\n<h1 id=\"mcetoc_1e6mi229fkf\" align=\"center\">VW5pdHkuIDotKQ==</h1>\n<h1 id=\"mcetoc_1e6mi229fkg\" align=\"center\">VW5pdHkuIDotKQ==</h1>\n<h1 id=\"mcetoc_1e6mi229fkh\" align=\"center\">VW5pdHkuIDotKQ==</h1>\n<h1 id=\"mcetoc_1e6mi229fki\" align=\"center\">VW5pdHkuIDotKQ==</h1>\n<h1 id=\"mcetoc_1e6mi229fkj\" align=\"center\">VW5pdHkuIDotKQ==</h1>\n<h1 id=\"mcetoc_1e6mi229fkk\" align=\"center\">VW5pdHkuIDotKQ==</h1>\n<h1 id=\"mcetoc_1e6mi229fkl\" align=\"center\">VW5pdHkuIDotKQ==</h1>\n<h1 id=\"mcetoc_1e6mi229fkm\" align=\"center\">VW5pdHkuIDotKQ==</h1>\n<h1 id=\"mcetoc_1e6mi229fkn\" align=\"center\">VW5pdHkuIDotKQ==</h1>\n<h1 id=\"mcetoc_1e6mi229fko\" align=\"center\">VW5pdHkuIDotKQ==</h1>\n<h1 id=\"mcetoc_1e6mi229fkp\" align=\"center\">VW5pdHkuIDotKQ==</h1>\n<h1 id=\"mcetoc_1e6mi229fkq\" align=\"center\">VW5pdHkuIDotKQ==</h1>\n<h1 id=\"mcetoc_1e6mi229fkr\" align=\"center\">VW5pdHkuIDotKQ==</h1>\n<h1 id=\"mcetoc_1e6mi229fks\" align=\"center\">VW5pdHkuIDotKQ==</h1>\n<h1 id=\"mcetoc_1e6mi229fkt\" align=\"center\">VW5pdHkuIDotKQ==</h1>\n<h1 id=\"mcetoc_1e6mi229fku\" align=\"center\">VW5pdHkuIDotKQ==</h1>\n<h1 id=\"mcetoc_1e6mi229fkv\" align=\"center\">VW5pdHkuIDotKQ==</h1>\n<h1 id=\"mcetoc_1e6mi229fl0\" align=\"center\">VW5pdHkuIDotKQ==</h1>\n<h1 id=\"mcetoc_1e6mi229fl1\" align=\"center\">VW5pdHkuIDotKQ==</h1>\n<h1 id=\"mcetoc_1e6mi229fl2\" align=\"center\">VW5pdHkuIDotKQ==</h1>\n<h1 id=\"mcetoc_1e6mi229fl3\" align=\"center\">VW5pdHkuIDotKQ==</h1>\n<h1 id=\"mcetoc_1e6mi229fl4\" align=\"center\">VW5pdHkuIDotKQ==</h1>\n<h1 id=\"mcetoc_1e6mi229fl5\" align=\"center\">VW5pdHkuIDotKQ==</h1>\n<h1 id=\"mcetoc_1e6mi229fl6\" align=\"center\">VW5pdHkuIDotKQ==</h1>\n<h1 id=\"mcetoc_1e6mi229fl7\" align=\"center\">VW5pdHkuIDotKQ==</h1>\n<h1 id=\"mcetoc_1e6mi229fl8\" align=\"center\">VW5pdHkuIDotKQ==</h1>\n<h1 id=\"mcetoc_1e6mi229fl9\" align=\"center\">VW5pdHkuIDotKQ==</h1>\n<h1 id=\"mcetoc_1e6mi229fla\" align=\"center\">VW5pdHkuIDotKQ==</h1>\n<h1 id=\"mcetoc_1e6mi229flb\" align=\"center\">VW5pdHkuIDotKQ==</h1>\n<h1 id=\"mcetoc_1e6mi229flc\" align=\"center\">VW5pdHkuIDotKQ==</h1>\n<h1 id=\"mcetoc_1e6mi229fld\" align=\"center\">VW5pdHkuIDotKQ==</h1>\n<h1 id=\"mcetoc_1e6mi229fle\" align=\"center\">VW5pdHkuIDotKQ==</h1>\n<h1 id=\"mcetoc_1e6mi229flf\" align=\"center\">VW5pdHkuIDotKQ==</h1>\n<h1 id=\"mcetoc_1e6mi229flg\" align=\"center\">VW5pdHkuIDotKQ==</h1>\n<h1 id=\"mcetoc_1e6mi229flh\" align=\"center\">VW5pdHkuIDotKQ==</h1>\n<h1 id=\"mcetoc_1e6mi229fli\" align=\"center\">VW5pdHkuIDotKQ==</h1>\n<h1 id=\"mcetoc_1e6mi229flj\" align=\"center\">VW5pdHkuIDotKQ==</h1>\n<h1 id=\"mcetoc_1e6mi229flk\" align=\"center\">VW5pdHkuIDotKQ==</h1>\n<h1 id=\"mcetoc_1e6mi229fll\" align=\"center\">VW5pdHkuIDotKQ==</h1>\n<h1 id=\"mcetoc_1e6mi229flm\" align=\"center\">VW5pdHkuIDotKQ==</h1>\n<h1 id=\"mcetoc_1e6mi229fln\" align=\"center\">VW5pdHkuIDotKQ==</h1>\n<h1 id=\"mcetoc_1e6mi229flo\" align=\"center\">VW5pdHkuIDotKQ==</h1>\n<h1 id=\"mcetoc_1e6mi229flp\" align=\"center\">VW5pdHkuIDotKQ==</h1>\n<h1 id=\"mcetoc_1e6mi229flq\" align=\"center\">VW5pdHkuIDotKQ==</h1>\n<h1 id=\"mcetoc_1e6mi229flr\" align=\"center\">VW5pdHkuIDotKQ==</h1>\n<h1 id=\"mcetoc_1e6mi229fls\" align=\"center\">VW5pdHkuIDotKQ==</h1>\n<h1 id=\"mcetoc_1e6mi229flt\" align=\"center\">VW5pdHkuIDotKQ==</h1>\n<h1 id=\"mcetoc_1e6mi229flu\" align=\"center\">VW5pdHkuIDotKQ==</h1>\n<h1 id=\"mcetoc_1e6mi229flv\" align=\"center\">VW5pdHkuIDotKQ==</h1>\n<h1 id=\"mcetoc_1e6mi229fm0\" align=\"center\">VW5pdHkuIDotKQ==</h1>\n<h1 id=\"mcetoc_1e6mi229fm1\" align=\"center\">VW5pdHkuIDotKQ==</h1>\n<h1 id=\"mcetoc_1e6mi229fm2\" align=\"center\">VW5pdHkuIDotKQ==</h1>\n<h1 id=\"mcetoc_1e6mi229fm3\" align=\"center\">VW5pdHkuIDotKQ==</h1>\n<h1 id=\"mcetoc_1e6mi229fm4\" align=\"center\">VW5pdHkuIDotKQ==</h1>\n<h1 id=\"mcetoc_1e6mi229fm5\" align=\"center\">VW5pdHkuIDotKQ==</h1>\n<h1 id=\"mcetoc_1e6mi229fm6\" align=\"center\">VW5pdHkuIDotKQ==</h1>\n<h1 id=\"mcetoc_1e6mi229fm7\" align=\"center\">VW5pdHkuIDotKQ==</h1>\n<h1 id=\"mcetoc_1e6mi229fm8\" align=\"center\">VW5pdHkuIDotKQ==</h1>\n<h1 id=\"mcetoc_1e6mi229fm9\" align=\"center\">VW5pdHkuIDotKQ==</h1>\n<h1 id=\"mcetoc_1e6mi229fma\" align=\"center\">VW5pdHkuIDotKQ==</h1>\n<h1 id=\"mcetoc_1e6mi229fmb\" align=\"center\">VW5pdHkuIDotKQ==</h1>\n<h1 id=\"mcetoc_1e6mi229fmc\" align=\"center\">VW5pdHkuIDotKQ==</h1>\n<h1 id=\"mcetoc_1e6mi229fmd\" align=\"center\">VW5pdHkuIDotKQ==</h1>\n<h1 id=\"mcetoc_1e6mi229fme\" align=\"center\">VW5pdHkuIDotKQ==</h1>\n<h1 id=\"mcetoc_1e6mi229fmf\" align=\"center\">VW5pdHkuIDotKQ==</h1>\n<h1 id=\"mcetoc_1e6mi229fmg\" align=\"center\">VW5pdHkuIDotKQ==</h1>\n<h1 id=\"mcetoc_1e6mi229fmh\" align=\"center\">VW5pdHkuIDotKQ==</h1>\n<h1 id=\"mcetoc_1e6mi229fmi\" align=\"center\">VW5pdHkuIDotKQ==</h1>\n<h1 id=\"mcetoc_1e6mi229fmj\" align=\"center\">VW5pdHkuIDotKQ==</h1>\n<h1 id=\"mcetoc_1e6mi229fmk\" align=\"center\">VW5pdHkuIDotKQ==</h1>\n<h1 id=\"mcetoc_1e6mi229fml\" align=\"center\">VW5pdHkuIDotKQ==</h1>\n<h1 id=\"mcetoc_1e6mi229fmm\" align=\"center\">VW5pdHkuIDotKQ==</h1>\n<h1 id=\"mcetoc_1e6mi229fmn\" align=\"center\">VW5pdHkuIDotKQ==</h1>\n<h1 id=\"mcetoc_1e6mi229fmo\" align=\"center\">VW5pdHkuIDotKQ==</h1>\n<h1 id=\"mcetoc_1e6mi229fmp\" align=\"center\">VW5pdHkuIDotKQ==</h1>\n<h1 id=\"mcetoc_1e6mi229fmq\" align=\"center\">VW5pdHkuIDotKQ==</h1>\n<h1 id=\"mcetoc_1e6mi229fmr\" align=\"center\">VW5pdHkuIDotKQ==</h1>\n<h1 id=\"mcetoc_1e6mi229fms\" align=\"center\">VW5pdHkuIDotKQ==</h1>\n<h1 id=\"mcetoc_1e6mi229fmt\" align=\"center\">VW5pdHkuIDotKQ==</h1>\n<h1 id=\"mcetoc_1e6mi229fmu\" align=\"center\">VW5pdHkuIDotKQ==</h1>\n<h1 id=\"mcetoc_1e6mi229fmv\" align=\"center\">VW5pdHkuIDotKQ==</h1>\n<h1 id=\"mcetoc_1e6mi229fn0\" align=\"center\">VW5pdHkuIDotKQ==</h1>\n<h1 id=\"mcetoc_1e6mi229fn1\" align=\"center\">VW5pdHkuIDotKQ==</h1>\n<h1 id=\"mcetoc_1e6mi229fn2\" align=\"center\">VW5pdHkuIDotKQ==</h1>\n<h1 id=\"mcetoc_1e6mi229fn3\" align=\"center\">VW5pdHkuIDotKQ==</h1>\n<h1 id=\"mcetoc_1e6mi229fn4\" align=\"center\">VW5pdHkuIDotKQ==</h1>\n<h1 id=\"mcetoc_1e6mi229fn5\" align=\"center\">VW5pdHkuIDotKQ==</h1>\n<h1 id=\"mcetoc_1e6mi229fn6\" align=\"center\">VW5pdHkuIDotKQ==</h1>\n<h1 id=\"mcetoc_1e6mi229fn7\" align=\"center\">VW5pdHkuIDotKQ==</h1>\n<h1 id=\"mcetoc_1e6mi229fn8\" align=\"center\">VW5pdHkuIDotKQ==</h1>\n<h1 id=\"mcetoc_1e6mi229fn9\" align=\"center\">VW5pdHkuIDotKQ==</h1>\n<h1 id=\"mcetoc_1e6mi229fna\" align=\"center\">VW5pdHkuIDotKQ==</h1>\n<h1 id=\"mcetoc_1e6mi229fnb\" align=\"center\">VW5pdHkuIDotKQ==</h1>\n<h1 id=\"mcetoc_1e6mi229fnc\" align=\"center\">VW5pdHkuIDotKQ==</h1>\n<h1 id=\"mcetoc_1e6mi229fnd\" align=\"center\">VW5pdHkuIDotKQ==</h1>\n<h1 id=\"mcetoc_1e6mi229fne\" align=\"center\">VW5pdHkuIDotKQ==</h1>\n<h1 id=\"mcetoc_1e6mi229fnf\" align=\"center\">VW5pdHkuIDotKQ==</h1>\n<h1 id=\"mcetoc_1e6mi229fng\" align=\"center\">VW5pdHkuIDotKQ==</h1>\n<h1 id=\"mcetoc_1e6mi229fnh\" align=\"center\">VW5pdHkuIDotKQ==</h1>\n<h1 id=\"mcetoc_1e6mi229fni\" align=\"center\">VW5pdHkuIDotKQ==</h1>\n<h1 id=\"mcetoc_1e6mi229fnj\" align=\"center\">VW5pdHkuIDotKQ==</h1>\n<h1 id=\"mcetoc_1e6mi229fnk\" align=\"center\">VW5pdHkuIDotKQ==</h1>\n<h1 id=\"mcetoc_1e6mi229fnl\" align=\"center\">VW5pdHkuIDotKQ==</h1>\n<h1 id=\"mcetoc_1e6mi229fnm\" align=\"center\">VW5pdHkuIDotKQ==</h1>\n<h1 id=\"mcetoc_1e6mi229fnn\" align=\"center\">VW5pdHkuIDotKQ==</h1>\n<h1 id=\"mcetoc_1e6mi229fno\" align=\"center\">VW5pdHkuIDotKQ==</h1>\n<h1 id=\"mcetoc_1e6mi229fnp\" align=\"center\">VW5pdHkuIDotKQ==</h1>\n<h1 id=\"mcetoc_1e6mi229fnq\" align=\"center\">VW5pdHkuIDotKQ==</h1>\n<h1 id=\"mcetoc_1e6mi229fnr\" align=\"center\">VW5pdHkuIDotKQ==</h1>\n<h1 id=\"mcetoc_1e6mi229fns\" align=\"center\">VW5pdHkuIDotKQ==</h1>\n<h1 id=\"mcetoc_1e6mi229fnt\" align=\"center\">VW5pdHkuIDotKQ==</h1>\n<h1 id=\"mcetoc_1e6mi229fnu\" align=\"center\">VW5pdHkuIDotKQ==</h1>\n<h1 id=\"mcetoc_1e6mi229fnv\" align=\"center\">VW5pdHkuIDotKQ==</h1>\n<h1 id=\"mcetoc_1e6mi229fo0\" align=\"center\">VW5pdHkuIDotKQ==</h1>\n<h1 id=\"mcetoc_1e6mi229fo1\" align=\"center\">VW5pdHkuIDotKQ==</h1>\n<h1 id=\"mcetoc_1e6mi229fo2\" align=\"center\">VW5pdHkuIDotKQ==</h1>\n<h1 id=\"mcetoc_1e6mi229fo3\" align=\"center\">VW5pdHkuIDotKQ==</h1>\n<h1 id=\"mcetoc_1e6mi229fo4\" align=\"center\">VW5pdHkuIDotKQ==</h1>\n<h1 id=\"mcetoc_1e6mi229fo5\" align=\"center\">VW5pdHkuIDotKQ==</h1>\n<h1 id=\"mcetoc_1e6mi229fo6\" align=\"center\">VW5pdHkuIDotKQ==</h1>\n<h1 id=\"mcetoc_1e6mi229fo7\" align=\"center\">VW5pdHkuIDotKQ==</h1>\n<h1 id=\"mcetoc_1e6mi229fo8\" align=\"center\">VW5pdHkuIDotKQ==</h1>\n<h1 id=\"mcetoc_1e6mi229fo9\" align=\"center\">VW5pdHkuIDotKQ==</h1>\n<h1 id=\"mcetoc_1e6mi229foa\" align=\"center\">VW5pdHkuIDotKQ==</h1>\n<h1 id=\"mcetoc_1e6mi229fob\" align=\"center\">VW5pdHkuIDotKQ==</h1>\n<h1 id=\"mcetoc_1e6mi229foc\" align=\"center\">VW5pdHkuIDotKQ==</h1>\n<h1 id=\"mcetoc_1e6mi229fod\" align=\"center\">VW5pdHkuIDotKQ==</h1>\n<h1 id=\"mcetoc_1e6mi229foe\" align=\"center\">VW5pdHkuIDotKQ==</h1>\n<h1 id=\"mcetoc_1e6mi229fof\" align=\"center\">VW5pdHkuIDotKQ==</h1>\n<h1 id=\"mcetoc_1e6mi229fog\" align=\"center\">VW5pdHkuIDotKQ==</h1>\n<h1 id=\"mcetoc_1e6mi229foh\" align=\"center\">VW5pdHkuIDotKQ==</h1>\n<h1 id=\"mcetoc_1e6mi229foi\" align=\"center\">VW5pdHkuIDotKQ==</h1>\n<h1 id=\"mcetoc_1e6mi229foj\" align=\"center\">VW5pdHkuIDotKQ==</h1>\n<h1 id=\"mcetoc_1e6mi229fok\" align=\"center\">VW5pdHkuIDotKQ==</h1>\n<h1 id=\"mcetoc_1e6mi229fol\" align=\"center\">VW5pdHkuIDotKQ==</h1>\n<h1 id=\"mcetoc_1e6mi229fom\" align=\"center\">VW5pdHkuIDotKQ==</h1>\n<h1 id=\"mcetoc_1e6mi229fon\" align=\"center\">VW5pdHkuIDotKQ==</h1>\n<h1 id=\"mcetoc_1e6mi229foo\" align=\"center\">VW5pdHkuIDotKQ==</h1>\n<h1 id=\"mcetoc_1e6mi229fop\" align=\"center\">VW5pdHkuIDotKQ==</h1>\n<h1 id=\"mcetoc_1e6mi229foq\" align=\"center\">VW5pdHkuIDotKQ==</h1>\n<h1 id=\"mcetoc_1e6mi229for\" align=\"center\">VW5pdHkuIDotKQ==</h1>\n<h1 id=\"mcetoc_1e6mi229fos\" align=\"center\">VW5pdHkuIDotKQ==</h1>\n<h1 id=\"mcetoc_1e6mi229fot\" align=\"center\">VW5pdHkuIDotKQ==</h1>\n<h1 id=\"mcetoc_1e6mi229fou\" align=\"center\">VW5pdHkuIDotKQ==</h1>\n<h1 id=\"mcetoc_1e6mi229fov\" align=\"center\">VW5pdHkuIDotKQ==</h1>\n<h1 id=\"mcetoc_1e6mi229fp0\" align=\"center\">VW5pdHkuIDotKQ==</h1>\n<h1 id=\"mcetoc_1e6mi229fp1\" align=\"center\">VW5pdHkuIDotKQ==</h1>\n<h1 id=\"mcetoc_1e6mi229fp2\" align=\"center\">VW5pdHkuIDotKQ==</h1>\n<h1 id=\"mcetoc_1e6mi229fp3\" align=\"center\">VW5pdHkuIDotKQ==</h1>\n<h1 id=\"mcetoc_1e6mi229fp4\" align=\"center\">VW5pdHkuIDotKQ==</h1>\n<h1 id=\"mcetoc_1e6mi229fp5\" align=\"center\">VW5pdHkuIDotKQ==</h1>\n<h1 id=\"mcetoc_1e6mi229fp6\" align=\"center\">VW5pdHkuIDotKQ==</h1>\n<h1 id=\"mcetoc_1e6mi229fp7\" align=\"center\">VW5pdHkuIDotKQ==</h1>\n<h1 id=\"mcetoc_1e6mi229fp8\" align=\"center\">VW5pdHkuIDotKQ==</h1>\n<h1 id=\"mcetoc_1e6mi229fp9\" align=\"center\">VW5pdHkuIDotKQ==</h1>\n<h1 id=\"mcetoc_1e6mi229fpa\" align=\"center\">VW5pdHkuIDotKQ==</h1>\n<h1 id=\"mcetoc_1e6mi229fpb\" align=\"center\">VW5pdHkuIDotKQ==</h1>\n<h1 id=\"mcetoc_1e6mi229fpc\" align=\"center\">VW5pdHkuIDotKQ==</h1>\n<h1 id=\"mcetoc_1e6mi229fpd\" align=\"center\">VW5pdHkuIDotKQ==</h1>\n<h1 id=\"mcetoc_1e6mi229fpe\" align=\"center\">VW5pdHkuIDotKQ==</h1>\n<h1 id=\"mcetoc_1e6mi229fpf\" align=\"center\">VW5pdHkuIDotKQ==</h1>\n<h1 id=\"mcetoc_1e6mi229fpg\" align=\"center\">VW5pdHkuIDotKQ==</h1>\n<h1 id=\"mcetoc_1e6mi229fph\" align=\"center\">VW5pdHkuIDotKQ==</h1>\n<h1 id=\"mcetoc_1e6mi229fpi\" align=\"center\">VW5pdHkuIDotKQ==</h1>\n<h1 id=\"mcetoc_1e6mi229fpj\" align=\"center\">VW5pdHkuIDotKQ==</h1>\n<h1 id=\"mcetoc_1e6mi229fpk\" align=\"center\">VW5pdHkuIDotKQ==</h1>\n<h1 id=\"mcetoc_1e6mi229fpl\" align=\"center\">VW5pdHkuIDotKQ==</h1>\n<h1 id=\"mcetoc_1e6mi229fpm\" align=\"center\">VW5pdHkuIDotKQ==</h1>\n<h1 id=\"mcetoc_1e6mi229fpn\" align=\"center\">VW5pdHkuIDotKQ==</h1>\n<h1 id=\"mcetoc_1e6mi229fpo\" align=\"center\">VW5pdHkuIDotKQ==</h1>\n<h1 id=\"mcetoc_1e6mi229fpp\" align=\"center\">VW5pdHkuIDotKQ==</h1>\n<h1 id=\"mcetoc_1e6mi229fpq\" align=\"center\">VW5pdHkuIDotKQ==</h1>\n<h1 id=\"mcetoc_1e6mi229fpr\" align=\"center\">VW5pdHkuIDotKQ==</h1>\n<h1 id=\"mcetoc_1e6mi229gps\" align=\"center\">VW5pdHkuIDotKQ==</h1>\n<h1 id=\"mcetoc_1e6mi229gpt\" align=\"center\">VW5pdHkuIDotKQ==</h1>\n<h1 id=\"mcetoc_1e6mi229gpu\" align=\"center\">VW5pdHkuIDotKQ==</h1>\n<h1 id=\"mcetoc_1e6mi229gpv\" align=\"center\">VW5pdHkuIDotKQ==</h1>\n<h1 id=\"mcetoc_1e6mi229gq0\" align=\"center\">VW5pdHkuIDotKQ==</h1>\n<h1 id=\"mcetoc_1e6mi229gq1\" align=\"center\">VW5pdHkuIDotKQ==</h1>\n<h1 id=\"mcetoc_1e6mi229gq2\" align=\"center\">VW5pdHkuIDotKQ==</h1>\n<h1 id=\"mcetoc_1e6mi229gq3\" align=\"center\">VW5pdHkuIDotKQ==</h1>\n<h1 id=\"mcetoc_1e6mi229gq4\" align=\"center\">VW5pdHkuIDotKQ==</h1>\n<h1 id=\"mcetoc_1e6mi229gq5\" align=\"center\">VW5pdHkuIDotKQ==</h1>\n<h1 id=\"mcetoc_1e6mi229gq6\" align=\"center\">VW5pdHkuIDotKQ==</h1>\n<h1 id=\"mcetoc_1e6mi229gq7\" align=\"center\">VW5pdHkuIDotKQ==</h1>\n<h1 id=\"mcetoc_1e6mi229gq8\" align=\"center\">VW5pdHkuIDotKQ==</h1>\n<h1 id=\"mcetoc_1e6mi229gq9\" align=\"center\">VW5pdHkuIDotKQ==</h1>\n<h1 id=\"mcetoc_1e6mi229gqa\" align=\"center\">VW5pdHkuIDotKQ==</h1>\n<h1 id=\"mcetoc_1e6mi229gqb\" align=\"center\">VW5pdHkuIDotKQ==</h1>\n<h1 id=\"mcetoc_1e6mi229gqc\" align=\"center\">VW5pdHkuIDotKQ==</h1>\n<h1 id=\"mcetoc_1e6mi229gqd\" align=\"center\">VW5pdHkuIDotKQ==</h1>\n<h1 id=\"mcetoc_1e6mi229gqe\" align=\"center\">VW5pdHkuIDotKQ==</h1>\n<h1 id=\"mcetoc_1e6mi229gqf\" align=\"center\">VW5pdHkuIDotKQ==</h1>\n<h1 id=\"mcetoc_1e6mi229gqg\" align=\"center\">VW5pdHkuIDotKQ==</h1>\n<h1 id=\"mcetoc_1e6mi229gqh\" align=\"center\">VW5pdHkuIDotKQ==</h1>\n<h1 id=\"mcetoc_1e6mi229gqi\" align=\"center\">VW5pdHkuIDotKQ==</h1>\n<h1 id=\"mcetoc_1e6mi229gqj\" align=\"center\">VW5pdHkuIDotKQ==</h1>\n<h1 id=\"mcetoc_1e6mi229gqk\" align=\"center\">VW5pdHkuIDotKQ==</h1>\n<h1 id=\"mcetoc_1e6mi229gql\" align=\"center\">VW5pdHkuIDotKQ==</h1>\n<h1 id=\"mcetoc_1e6mi229gqm\" align=\"center\">VW5pdHkuIDotKQ==</h1>\n<h1 id=\"mcetoc_1e6mi229gqn\" align=\"center\">VW5pdHkuIDotKQ==</h1>\n<h1 id=\"mcetoc_1e6mi229gqo\" align=\"center\">VW5pdHkuIDotKQ==</h1>\n<h1 id=\"mcetoc_1e6mi229gqp\" align=\"center\">VW5pdHkuIDotKQ==</h1>\n<h1 id=\"mcetoc_1e6mi229gqq\" align=\"center\">VW5pdHkuIDotKQ==</h1>\n<h1 id=\"mcetoc_1e6mi229gqr\" align=\"center\">VW5pdHkuIDotKQ==</h1>\n<h1 id=\"mcetoc_1e6mi229gqs\" align=\"center\">VW5pdHkuIDotKQ==</h1>\n<h1 id=\"mcetoc_1e6mi229gqt\" align=\"center\">VW5pdHkuIDotKQ==</h1>\n<h1 id=\"mcetoc_1e6mi229gqu\" align=\"center\">VW5pdHkuIDotKQ==</h1>\n<h1 id=\"mcetoc_1e6mi229gqv\" align=\"center\">VW5pdHkuIDotKQ==</h1>\n<h1 id=\"mcetoc_1e6mi229gr0\" align=\"center\">VW5pdHkuIDotKQ==</h1>\n<h1 id=\"mcetoc_1e6mi229gr1\" align=\"center\">VW5pdHkuIDotKQ==</h1>\n<h1 id=\"mcetoc_1e6mi229gr2\" align=\"center\">VW5pdHkuIDotKQ==</h1>\n<h1 id=\"mcetoc_1e6mi229gr3\" align=\"center\">VW5pdHkuIDotKQ==</h1>\n<h1 id=\"mcetoc_1e6mi229gr4\" align=\"center\">VW5pdHkuIDotKQ==</h1>\n<h1 id=\"mcetoc_1e6mi229gr5\" align=\"center\">VW5pdHkuIDotKQ==</h1>\n<h1 id=\"mcetoc_1e6mi229gr6\" align=\"center\">VW5pdHkuIDotKQ==</h1>\n<h1 id=\"mcetoc_1e6mi229gr7\" align=\"center\">VW5pdHkuIDotKQ==</h1>\n<h1 id=\"mcetoc_1e6mi229gr8\" align=\"center\">VW5pdHkuIDotKQ==</h1>\n<h1 id=\"mcetoc_1e6mi229gr9\" align=\"center\">VW5pdHkuIDotKQ==</h1>\n<h1 id=\"mcetoc_1e6mi229gra\" align=\"center\">VW5pdHkuIDotKQ==</h1>\n<h1 id=\"mcetoc_1e6mi229grb\" align=\"center\">VW5pdHkuIDotKQ==</h1>\n<h1 id=\"mcetoc_1e6mi229grc\" align=\"center\">VW5pdHkuIDotKQ==</h1>\n<h1 id=\"mcetoc_1e6mi229grd\" align=\"center\">VW5pdHkuIDotKQ==</h1>\n<h1 id=\"mcetoc_1e6mi229gre\" align=\"center\">VW5pdHkuIDotKQ==</h1>\n<h1 id=\"mcetoc_1e6mi229grf\" align=\"center\">VW5pdHkuIDotKQ==</h1>\n<h1 id=\"mcetoc_1e6mi229grg\" align=\"center\">VW5pdHkuIDotKQ==</h1>\n<h1 id=\"mcetoc_1e6mi229grh\" align=\"center\">VW5pdHkuIDotKQ==</h1>\n<h1 id=\"mcetoc_1e6mi229gri\" align=\"center\">VW5pdHkuIDotKQ==</h1>\n<h1 id=\"mcetoc_1e6mi229grj\" align=\"center\">VW5pdHkuIDotKQ==</h1>\n<h1 id=\"mcetoc_1e6mi229grk\" align=\"center\">VW5pdHkuIDotKQ==</h1>\n<h1 id=\"mcetoc_1e6mi229grl\" align=\"center\">VW5pdHkuIDotKQ==</h1>\n<h1 id=\"mcetoc_1e6mi229grm\" align=\"center\">VW5pdHkuIDotKQ==</h1>\n<h1 id=\"mcetoc_1e6mi229grn\" align=\"center\">VW5pdHkuIDotKQ==</h1>\n<h1 id=\"mcetoc_1e6mi229gro\" align=\"center\">VW5pdHkuIDotKQ==</h1>\n<h1 id=\"mcetoc_1e6mi229grp\" align=\"center\">VW5pdHkuIDotKQ==</h1>\n<h1 id=\"mcetoc_1e6mi229grq\" align=\"center\">VW5pdHkuIDotKQ==</h1>\n<h1 id=\"mcetoc_1e6mi229grr\" align=\"center\">VW5pdHkuIDotKQ==</h1>\n<h1 id=\"mcetoc_1e6mi229grs\" align=\"center\">VW5pdHkuIDotKQ==</h1>\n<h1 id=\"mcetoc_1e6mi229grt\" align=\"center\">VW5pdHkuIDotKQ==</h1>\n<h1 id=\"mcetoc_1e6mi229gru\" align=\"center\">VW5pdHkuIDotKQ==</h1>\n<h1 id=\"mcetoc_1e6mi229grv\" align=\"center\">VW5pdHkuIDotKQ==</h1>\n<h1 id=\"mcetoc_1e6mi229gs0\" align=\"center\">VW5pdHkuIDotKQ==</h1>\n<h1 id=\"mcetoc_1e6mi229gs1\" align=\"center\">VW5pdHkuIDotKQ==</h1>\n<h1 id=\"mcetoc_1e6mi229gs2\" align=\"center\">VW5pdHkuIDotKQ==</h1>\n<h1 id=\"mcetoc_1e6mi229gs3\" align=\"center\">VW5pdHkuIDotKQ==</h1>\n<h1 id=\"mcetoc_1e6mi229gs4\" align=\"center\">VW5pdHkuIDotKQ==</h1>\n<h1 id=\"mcetoc_1e6mi229gs5\" align=\"center\">VW5pdHkuIDotKQ==</h1>\n<h1 id=\"mcetoc_1e6mi229gs6\" align=\"center\">VW5pdHkuIDotKQ==</h1>\n<h1 id=\"mcetoc_1e6mi229gs7\" align=\"center\">VW5pdHkuIDotKQ==</h1>\n<h1 id=\"mcetoc_1e6mi229gs8\" align=\"center\">VW5pdHkuIDotKQ==</h1>\n<h1 id=\"mcetoc_1e6mi229gs9\" align=\"center\">VW5pdHkuIDotKQ==</h1>\n<h1 id=\"mcetoc_1e6mi229gsa\" align=\"center\">VW5pdHkuIDotKQ==</h1>\n<h1 id=\"mcetoc_1e6mi229gsb\" align=\"center\">VW5pdHkuIDotKQ==</h1>\n<h1 id=\"mcetoc_1e6mi229gsc\" align=\"center\">VW5pdHkuIDotKQ==</h1>\n<h1 id=\"mcetoc_1e6mi229gsd\" align=\"center\">VW5pdHkuIDotKQ==</h1>\n<h1 id=\"mcetoc_1e6mi229gse\" align=\"center\">VW5pdHkuIDotKQ==</h1>\n<h1 id=\"mcetoc_1e6mi229gsf\" align=\"center\">VW5pdHkuIDotKQ==</h1>\n<h1 id=\"mcetoc_1e6mi229gsg\" align=\"center\">VW5pdHkuIDotKQ==</h1>\n<h1 id=\"mcetoc_1e6mi229gsh\" align=\"center\">VW5pdHkuIDotKQ==</h1>\n<h1 id=\"mcetoc_1e6mi229gsi\" align=\"center\">VW5pdHkuIDotKQ==</h1>\n<h1 id=\"mcetoc_1e6mi229gsj\" align=\"center\">VW5pdHkuIDotKQ==</h1>\n<h1 id=\"mcetoc_1e6mi229gsk\" align=\"center\">VW5pdHkuIDotKQ==</h1>\n<h1 id=\"mcetoc_1e6mi229gsl\" align=\"center\">VW5pdHkuIDotKQ==</h1>\n<h1 id=\"mcetoc_1e6mi229gsm\" align=\"center\">VW5pdHkuIDotKQ==</h1>\n<h1 id=\"mcetoc_1e6mi229gsn\" align=\"center\">VW5pdHkuIDotKQ==</h1>\n<h1 id=\"mcetoc_1e6mi229gso\" align=\"center\">VW5pdHkuIDotKQ==</h1>\n<h1 id=\"mcetoc_1e6mi229gsp\" align=\"center\">VW5pdHkuIDotKQ==</h1>\n<h1 id=\"mcetoc_1e6mi229gsq\" align=\"center\">VW5pdHkuIDotKQ==</h1>\n<h1 id=\"mcetoc_1e6mi229gsr\" align=\"center\">VW5pdHkuIDotKQ==</h1>\n<h1 id=\"mcetoc_1e6mi229gss\" align=\"center\">VW5pdHkuIDotKQ==</h1>\n<h1 id=\"mcetoc_1e6mi229gst\" align=\"center\">VW5pdHkuIDotKQ==</h1>\n<h1 id=\"mcetoc_1e6mi229gsu\" align=\"center\">VW5pdHkuIDotKQ==</h1>\n<h1 id=\"mcetoc_1e6mi229gsv\" align=\"center\">VW5pdHkuIDotKQ==</h1>\n<h1 id=\"mcetoc_1e6mi229gt0\" align=\"center\">VW5pdHkuIDotKQ==</h1>\n<h1 id=\"mcetoc_1e6mi229gt1\" align=\"center\">VW5pdHkuIDotKQ==</h1>\n<h1 id=\"mcetoc_1e6mi229gt2\" align=\"center\">VW5pdHkuIDotKQ==</h1>\n<h1 id=\"mcetoc_1e6mi229gt3\" align=\"center\">VW5pdHkuIDotKQ==</h1>\n<h1 id=\"mcetoc_1e6mi229gt4\" align=\"center\">VW5pdHkuIDotKQ==</h1>\n<h1 id=\"mcetoc_1e6mi229gt5\" align=\"center\">VW5pdHkuIDotKQ==</h1>\n<h1 id=\"mcetoc_1e6mi229gt6\" align=\"center\">VW5pdHkuIDotKQ==</h1>\n<h1 id=\"mcetoc_1e6mi229gt7\" align=\"center\">VW5pdHkuIDotKQ==</h1>\n<h1 id=\"mcetoc_1e6mi229gt8\" align=\"center\">VW5pdHkuIDotKQ==</h1>\n<h1 id=\"mcetoc_1e6mi229gt9\" align=\"center\">VW5pdHkuIDotKQ==</h1>\n<h1 id=\"mcetoc_1e6mi229gta\" align=\"center\">VW5pdHkuIDotKQ==</h1>\n<h1 id=\"mcetoc_1e6mi229gtb\" align=\"center\">VW5pdHkuIDotKQ==</h1>\n<h1 id=\"mcetoc_1e6mi229gtc\" align=\"center\">VW5pdHkuIDotKQ==</h1>\n<h1 id=\"mcetoc_1e6mi229gtd\" align=\"center\">VW5pdHkuIDotKQ==</h1>\n<h1 id=\"mcetoc_1e6mi229gte\" align=\"center\">VW5pdHkuIDotKQ==</h1>\n<h1 id=\"mcetoc_1e6mi229gtf\" align=\"center\">VW5pdHkuIDotKQ==</h1>\n<h1 id=\"mcetoc_1e6mi229gtg\" align=\"center\">VW5pdHkuIDotKQ==</h1>\n<h1 id=\"mcetoc_1e6mi229gth\" align=\"center\">VW5pdHkuIDotKQ==</h1>\n<h1 id=\"mcetoc_1e6mi229gti\" align=\"center\">VW5pdHkuIDotKQ==</h1>\n<h1 id=\"mcetoc_1e6mi229gtj\" align=\"center\">VW5pdHkuIDotKQ==</h1>\n<h1 id=\"mcetoc_1e6mi229gtk\" align=\"center\">VW5pdHkuIDotKQ==</h1>\n<h1 id=\"mcetoc_1e6mi229gtl\" align=\"center\">VW5pdHkuIDotKQ==</h1>\n<h1 id=\"mcetoc_1e6mi229gtm\" align=\"center\">VW5pdHkuIDotKQ==</h1>\n<h1 id=\"mcetoc_1e6mi229gtn\" align=\"center\">VW5pdHkuIDotKQ==</h1>\n<h1 id=\"mcetoc_1e6mi229gto\" align=\"center\">VW5pdHkuIDotKQ==</h1>\n<h1 id=\"mcetoc_1e6mi229gtp\" align=\"center\">VW5pdHkuIDotKQ==</h1>\n<h1 id=\"mcetoc_1e6mi229gtq\" align=\"center\">VW5pdHkuIDotKQ==</h1>\n<h1 id=\"mcetoc_1e6mi229gtr\" align=\"center\">VW5pdHkuIDotKQ==</h1>\n<h1 id=\"mcetoc_1e6mi229gts\" align=\"center\">VW5pdHkuIDotKQ==</h1>\n<h1 id=\"mcetoc_1e6mi229gtt\" align=\"center\">VW5pdHkuIDotKQ==</h1>\n<h1 id=\"mcetoc_1e6mi229gtu\" align=\"center\">VW5pdHkuIDotKQ==</h1>\n<h1 id=\"mcetoc_1e6mi229gtv\" align=\"center\">VW5pdHkuIDotKQ==</h1>\n<h1 id=\"mcetoc_1e6mi229gu0\" align=\"center\">VW5pdHkuIDotKQ==</h1>\n<h1 id=\"mcetoc_1e6mi229gu1\" align=\"center\">VW5pdHkuIDotKQ==</h1>\n<h1 id=\"mcetoc_1e6mi229gu2\" align=\"center\">VW5pdHkuIDotKQ==</h1>\n<h1 id=\"mcetoc_1e6mi229gu3\" align=\"center\">VW5pdHkuIDotKQ==</h1>\n<h1 id=\"mcetoc_1e6mi229gu4\" align=\"center\">VW5pdHkuIDotKQ==</h1>\n<h1 id=\"mcetoc_1e6mi229gu5\" align=\"center\">VW5pdHkuIDotKQ==</h1>\n<h1 id=\"mcetoc_1e6mi229gu6\" align=\"center\">VW5pdHkuIDotKQ==</h1>\n<h1 id=\"mcetoc_1e6mi229gu7\" align=\"center\">VW5pdHkuIDotKQ==</h1>\n<h1 id=\"mcetoc_1e6mi229gu8\" align=\"center\">VW5pdHkuIDotKQ==</h1>\n<h1 id=\"mcetoc_1e6mi229gu9\" align=\"center\">VW5pdHkuIDotKQ==</h1>\n<h1 id=\"mcetoc_1e6mi229gua\" align=\"center\">VW5pdHkuIDotKQ==</h1>\n<h1 id=\"mcetoc_1e6mi229gub\" align=\"center\">VW5pdHkuIDotKQ==</h1>\n<h1 id=\"mcetoc_1e6mi229guc\" align=\"center\">VW5pdHkuIDotKQ==</h1>\n<h1 id=\"mcetoc_1e6mi229gud\" align=\"center\">VW5pdHkuIDotKQ==</h1>\n<h1 id=\"mcetoc_1e6mi229gue\" align=\"center\">VW5pdHkuIDotKQ==</h1>\n<h1 id=\"mcetoc_1e6mi229guf\" align=\"center\">VW5pdHkuIDotKQ==</h1>\n<h1 id=\"mcetoc_1e6mi229gug\" align=\"center\">VW5pdHkuIDotKQ==</h1>\n<h1 id=\"mcetoc_1e6mi229guh\" align=\"center\">VW5pdHkuIDotKQ==</h1>\n<h1 id=\"mcetoc_1e6mi229gui\" align=\"center\">VW5pdHkuIDotKQ==</h1>\n<h1 id=\"mcetoc_1e6mi229guj\" align=\"center\">VW5pdHkuIDotKQ==</h1>\n<h1 id=\"mcetoc_1e6mi229guk\" align=\"center\">VW5pdHkuIDotKQ==</h1>\n<h1 id=\"mcetoc_1e6mi229gul\" align=\"center\">VW5pdHkuIDotKQ==</h1>\n<h1 id=\"mcetoc_1e6mi229gum\" align=\"center\">VW5pdHkuIDotKQ==</h1>\n<h1 id=\"mcetoc_1e6mi229gun\" align=\"center\">VW5pdHkuIDotKQ==</h1>\n<h1 id=\"mcetoc_1e6mi229guo\" align=\"center\">VW5pdHkuIDotKQ==</h1>\n<h1 id=\"mcetoc_1e6mi229gup\" align=\"center\">VW5pdHkuIDotKQ==</h1>",
            "author": {
                "name": "TheCrafters001"
            },
            "tags": [
            ],
            "date_published": "2020-04-24T12:59:26-04:00",
            "date_modified": "2020-04-24T12:59:26-04:00"
        },
        {
            "id": "https://thecrafters001.ga/most-games-and-software-have-been-added/",
            "url": "https://thecrafters001.ga/most-games-and-software-have-been-added/",
            "title": "Most Games and Software Have Been Added!",
            "summary": "I have added most of my Software and Games back to my site. I will not add all of them as most of them are either canceled or no-longer supported.",
            "content_html": "<p>I have added most of my Software and Games back to my site. I will not add all of them as most of them are either canceled or no-longer supported.</p>",
            "author": {
                "name": "TheCrafters001"
            },
            "tags": [
            ],
            "date_published": "2020-04-24T12:44:25-04:00",
            "date_modified": "2020-04-24T12:44:25-04:00"
        },
        {
            "id": "https://thecrafters001.ga/how-do-i-access-old-site-stuff-ie-games-software-etc/",
            "url": "https://thecrafters001.ga/how-do-i-access-old-site-stuff-ie-games-software-etc/",
            "title": "How do I access old site stuff (ie: games, software, etc.)",
            "summary": "Well, I am working on that. I plan to make hidden post that contain the links to other hidden post that have software/games/etc in them. But it will take some time. Once it is up am running, I will be sure to post about it!",
            "content_html": "Well, I am working on that. I plan to make hidden post that contain the links to other hidden post that have software/games/etc in them. But it will take some time. Once it is up am running, I will be sure to post about it!",
            "author": {
                "name": "TheCrafters001"
            },
            "tags": [
                   "Help"
            ],
            "date_published": "2020-04-22T20:14:53-04:00",
            "date_modified": "2020-04-22T20:14:53-04:00"
        },
        {
            "id": "https://thecrafters001.ga/new-website-design/",
            "url": "https://thecrafters001.ga/new-website-design/",
            "title": "New Website Design",
            "summary": "Hi! I have redesigned the website!",
            "content_html": "Hi! I have redesigned the website!",
            "author": {
                "name": "TheCrafters001"
            },
            "tags": [
            ],
            "date_published": "2020-04-21T21:49:10-04:00",
            "date_modified": "2020-04-21T21:49:54-04:00"
        }
    ]
}
